Workbook
Name Print_Area: 'Справочник типов'!$A$1:$J$27

Sheet Итого по проекту
A1: Итого по проекту — универсальный расчёт стоимости
A2: Тип проекта и этапы могут быть загружены из результата нейросети; жёлтые ячейки допускают ручную корректировку
A4: Карточка оценки
A5: Проект | B5: =IF(Ввод!$B$4="","",Ввод!$B$4) | D5: Дата оценки | E5: =IF(Ввод!$B$6="","",Ввод!$B$6) | G5: КЛЮЧЕВОЙ ИТОГ
A6: Тип проекта | B6: =IF(Ввод!$B$5="","",Ввод!$B$5) | D6: Уверенность | E6: =Ввод!$B$8 -> 0.7 | G6: Цена без НДС | I6: =((SUM(Расчёт!$Q$6:$Q$105)+SUM('Внешние затраты'!$J$6:$J$25))+((SUM(Расчёт!$Q$6:$Q$105)+SUM('Внешние затраты'!$J$6:$J$25))*Ввод!$B$16))*(1-Ввод!$B$10) -> 0
A7: Продукт | B7: =Ввод!$E$5 | D7: Категория | E7: =Ввод!$E$7 | G7: НДС | I7: =((SUM(Расчёт!$Q$6:$Q$105)+SUM('Внешние затраты'!$J$6:$J$25))+((SUM(Расчёт!$Q$6:$Q$105)+SUM('Внешние затраты'!$J$6:$J$25))*Ввод!$B$16))*(1-Ввод!$B$10)*Ввод!$B$9 -> 0
A8: Направление | B8: =Ввод!$E$4 | D8: Тип сделки | E8: =Ввод!$E$9 | G8: Цена с НДС | I8: =((SUM(Расчёт!$Q$6:$Q$105)+SUM('Внешние затраты'!$J$6:$J$25))+((SUM(Расчёт!$Q$6:$Q$105)+SUM('Внешние затраты'!$J$6:$J$25))*Ввод!$B$16))*(1-Ввод!$B$10)*(1+Ввод!$B$9) -> 0
A9: Расчётная модель | B9: =Ввод!$E$6 | D9: Ориентир срока, мес. | E9: =Ввод!$E$8 | G9: Себестоимость | I9: =(SUM(Расчёт!$R$6:$R$105)+SUM('Внешние затраты'!$I$6:$I$25)) -> 0
A10: Режим оценки | B10: =Ввод!$B$7 -> Бюджетная | D10: Базис часов | E10: =Ввод!$E$10 | G10: Валовая маржа | I10: =IFERROR((((SUM(Расчёт!$Q$6:$Q$105)+SUM('Внешние затраты'!$J$6:$J$25))+((SUM(Расчёт!$Q$6:$Q$105)+SUM('Внешние затраты'!$J$6:$J$25))*Ввод!$B$16))*(1-Ввод!$B$10)-(SUM(Расчёт!$R$6:$R$105)+SUM('Внешние затраты'!$I$6:$I$25)))/((SUM(Расчёт!$Q$6:$Q$105)+SUM('Внешние затраты'!$J$6:$J$25))+((SUM(Расчёт!$Q$6:$Q$105)+SUM('Внешние затраты'!$J$6:$J$25))*Ввод!$B$16))*(1-Ввод!$B$10),0) -> 0
A11: Статус модели | B11: =Проверки!$B$3 -> FAIL | D11: Срок результата | E11: =IF(Ввод!$B$5="","",IF(OR(Ввод!$E$9="Возобновляемая",Ввод!$E$6="Поддержка",Ввод!$E$6="Облако",Ввод!$E$6="Подписка",Ввод!$E$6="Аренда"),MAX(1,SUMIF(Ввод!$G$20:$G$27,"TERM_MONTHS",Ввод!$E$20:$E$27))&" мес.",ROUNDUP(SUM(Расчёт!$S$6:$S$105)+SUMIF(Ввод!$G$20:$G$27,"LEAD_DAYS",Ввод!$E$20:$E$27),0)&" раб. дн."))
A14: Ключевые параметры выбранного типа
A15: Параметр | B15: Ед. | C15: Принятое значение | D15: Обязателен | E15: Как влияет | G15: Состав цены | H15: База | I15: Корректировка | J15: Итого
A16: =Ввод!$B$20 | B16: =Ввод!$C$20 | C16: =Ввод!$E$20 | D16: =Ввод!$F$20 | E16: =Ввод!$H$20 | G16: Труд по ставкам | H16: =SUM(Расчёт!$Q$6:$Q$105) -> 0 | J16: =H16 -> 0
A17: =Ввод!$B$21 | B17: =Ввод!$C$21 | C17: =Ввод!$E$21 | D17: =Ввод!$F$21 | E17: =Ввод!$H$21 | G17: Внешние затраты | H17: =SUM('Внешние затраты'!$J$6:$J$25) -> 0 | J17: =H17 -> 0
A18: =Ввод!$B$22 | B18: =Ввод!$C$22 | C18: =Ввод!$E$22 | D18: =Ввод!$F$22 | E18: =Ввод!$H$22 | G18: База расчёта | H18: =SUM(Расчёт!$Q$6:$Q$105)+SUM('Внешние затраты'!$J$6:$J$25) -> 0 | J18: =H18 -> 0
A19: =Ввод!$B$23 | B19: =Ввод!$C$23 | C19: =Ввод!$E$23 | D19: =Ввод!$F$23 | E19: =Ввод!$H$23 | G19: БФ / коммерческий резерв | I19: =Ввод!$B$16 -> 0 | J19: =(SUM(Расчёт!$Q$6:$Q$105)+SUM('Внешние затраты'!$J$6:$J$25))*Ввод!$B$16 -> 0
A20: =Ввод!$B$24 | B20: =Ввод!$C$24 | C20: =Ввод!$E$24 | D20: =Ввод!$F$24 | E20: =Ввод!$H$24 | G20: Цена до скидки | J20: =(SUM(Расчёт!$Q$6:$Q$105)+SUM('Внешние затраты'!$J$6:$J$25))+((SUM(Расчёт!$Q$6:$Q$105)+SUM('Внешние затраты'!$J$6:$J$25))*Ввод!$B$16) -> 0
A21: =Ввод!$B$25 | B21: =Ввод!$C$25 | C21: =Ввод!$E$25 | D21: =Ввод!$F$25 | E21: =Ввод!$H$25 | G21: Скидка | I21: =Ввод!$B$10 -> 0 | J21: =-((SUM(Расчёт!$Q$6:$Q$105)+SUM('Внешние затраты'!$J$6:$J$25))+((SUM(Расчёт!$Q$6:$Q$105)+SUM('Внешние затраты'!$J$6:$J$25))*Ввод!$B$16))*Ввод!$B$10 -> 0
A22: =Ввод!$B$26 | B22: =Ввод!$C$26 | C22: =Ввод!$E$26 | D22: =Ввод!$F$26 | E22: =Ввод!$H$26 | G22: Цена без НДС | J22: =((SUM(Расчёт!$Q$6:$Q$105)+SUM('Внешние затраты'!$J$6:$J$25))+((SUM(Расчёт!$Q$6:$Q$105)+SUM('Внешние затраты'!$J$6:$J$25))*Ввод!$B$16))*(1-Ввод!$B$10) -> 0
A23: =Ввод!$B$27 | B23: =Ввод!$C$27 | C23: =Ввод!$E$27 | D23: =Ввод!$F$27 | E23: =Ввод!$H$27 | G23: НДС | J23: =((SUM(Расчёт!$Q$6:$Q$105)+SUM('Внешние затраты'!$J$6:$J$25))+((SUM(Расчёт!$Q$6:$Q$105)+SUM('Внешние затраты'!$J$6:$J$25))*Ввод!$B$16))*(1-Ввод!$B$10)*Ввод!$B$9 -> 0
G24: Цена с НДС | J24: =((SUM(Расчёт!$Q$6:$Q$105)+SUM('Внешние затраты'!$J$6:$J$25))+((SUM(Расчёт!$Q$6:$Q$105)+SUM('Внешние затраты'!$J$6:$J$25))*Ввод!$B$16))*(1-Ввод!$B$10)*(1+Ввод!$B$9) -> 0
A26: Итоги по этапам | H26: Допущения и вопросы
A27: № | B27: Этап | C27: Часы | D27: Цена | E27: Себестоимость | F27: Экв. раб. дни | H27: Тип | I27: Формулировка | J27: Влияние
A28: =IF(B28="","",1) | B28: =IFERROR(INDEX(Расчёт!$B$6:$B$105,MATCH(1,Расчёт!$A$6:$A$105,0)),"") | C28: =IF(B28="","",SUMIF(Расчёт!$A$6:$A$105,1,Расчёт!$P$6:$P$105)) | D28: =IF(B28="","",SUMIF(Расчёт!$A$6:$A$105,1,Расчёт!$Q$6:$Q$105)) | E28: =IF(B28="","",SUMIF(Расчёт!$A$6:$A$105,1,Расчёт!$R$6:$R$105)) | F28: =IF(B28="","",SUMIF(Расчёт!$A$6:$A$105,1,Расчёт!$S$6:$S$105)) | H28: =IF(Ввод!$A$32="","",Ввод!$A$32) | I28: =IF(Ввод!$B$32="","",Ввод!$B$32) | J28: =IF(Ввод!$D$32="","",Ввод!$D$32)
A29: =IF(B29="","",2) | B29: =IFERROR(INDEX(Расчёт!$B$6:$B$105,MATCH(2,Расчёт!$A$6:$A$105,0)),"") | C29: =IF(B29="","",SUMIF(Расчёт!$A$6:$A$105,2,Расчёт!$P$6:$P$105)) | D29: =IF(B29="","",SUMIF(Расчёт!$A$6:$A$105,2,Расчёт!$Q$6:$Q$105)) | E29: =IF(B29="","",SUMIF(Расчёт!$A$6:$A$105,2,Расчёт!$R$6:$R$105)) | F29: =IF(B29="","",SUMIF(Расчёт!$A$6:$A$105,2,Расчёт!$S$6:$S$105)) | H29: =IF(Ввод!$A$33="","",Ввод!$A$33) | I29: =IF(Ввод!$B$33="","",Ввод!$B$33) | J29: =IF(Ввод!$D$33="","",Ввод!$D$33)
A30: =IF(B30="","",3) | B30: =IFERROR(INDEX(Расчёт!$B$6:$B$105,MATCH(3,Расчёт!$A$6:$A$105,0)),"") | C30: =IF(B30="","",SUMIF(Расчёт!$A$6:$A$105,3,Расчёт!$P$6:$P$105)) | D30: =IF(B30="","",SUMIF(Расчёт!$A$6:$A$105,3,Расчёт!$Q$6:$Q$105)) | E30: =IF(B30="","",SUMIF(Расчёт!$A$6:$A$105,3,Расчёт!$R$6:$R$105)) | F30: =IF(B30="","",SUMIF(Расчёт!$A$6:$A$105,3,Расчёт!$S$6:$S$105)) | H30: =IF(Ввод!$A$34="","",Ввод!$A$34) | I30: =IF(Ввод!$B$34="","",Ввод!$B$34) | J30: =IF(Ввод!$D$34="","",Ввод!$D$34)
A31: =IF(B31="","",4) | B31: =IFERROR(INDEX(Расчёт!$B$6:$B$105,MATCH(4,Расчёт!$A$6:$A$105,0)),"") | C31: =IF(B31="","",SUMIF(Расчёт!$A$6:$A$105,4,Расчёт!$P$6:$P$105)) | D31: =IF(B31="","",SUMIF(Расчёт!$A$6:$A$105,4,Расчёт!$Q$6:$Q$105)) | E31: =IF(B31="","",SUMIF(Расчёт!$A$6:$A$105,4,Расчёт!$R$6:$R$105)) | F31: =IF(B31="","",SUMIF(Расчёт!$A$6:$A$105,4,Расчёт!$S$6:$S$105)) | H31: =IF(Ввод!$A$35="","",Ввод!$A$35) | I31: =IF(Ввод!$B$35="","",Ввод!$B$35) | J31: =IF(Ввод!$D$35="","",Ввод!$D$35)
A32: =IF(B32="","",5) | B32: =IFERROR(INDEX(Расчёт!$B$6:$B$105,MATCH(5,Расчёт!$A$6:$A$105,0)),"") | C32: =IF(B32="","",SUMIF(Расчёт!$A$6:$A$105,5,Расчёт!$P$6:$P$105)) | D32: =IF(B32="","",SUMIF(Расчёт!$A$6:$A$105,5,Расчёт!$Q$6:$Q$105)) | E32: =IF(B32="","",SUMIF(Расчёт!$A$6:$A$105,5,Расчёт!$R$6:$R$105)) | F32: =IF(B32="","",SUMIF(Расчёт!$A$6:$A$105,5,Расчёт!$S$6:$S$105)) | H32: =IF(Ввод!$A$36="","",Ввод!$A$36) | I32: =IF(Ввод!$B$36="","",Ввод!$B$36) | J32: =IF(Ввод!$D$36="","",Ввод!$D$36)
A33: =IF(B33="","",6) | B33: =IFERROR(INDEX(Расчёт!$B$6:$B$105,MATCH(6,Расчёт!$A$6:$A$105,0)),"") | C33: =IF(B33="","",SUMIF(Расчёт!$A$6:$A$105,6,Расчёт!$P$6:$P$105)) | D33: =IF(B33="","",SUMIF(Расчёт!$A$6:$A$105,6,Расчёт!$Q$6:$Q$105)) | E33: =IF(B33="","",SUMIF(Расчёт!$A$6:$A$105,6,Расчёт!$R$6:$R$105)) | F33: =IF(B33="","",SUMIF(Расчёт!$A$6:$A$105,6,Расчёт!$S$6:$S$105)) | H33: =IF(Ввод!$A$37="","",Ввод!$A$37) | I33: =IF(Ввод!$B$37="","",Ввод!$B$37) | J33: =IF(Ввод!$D$37="","",Ввод!$D$37)
A34: =IF(B34="","",7) | B34: =IFERROR(INDEX(Расчёт!$B$6:$B$105,MATCH(7,Расчёт!$A$6:$A$105,0)),"") | C34: =IF(B34="","",SUMIF(Расчёт!$A$6:$A$105,7,Расчёт!$P$6:$P$105)) | D34: =IF(B34="","",SUMIF(Расчёт!$A$6:$A$105,7,Расчёт!$Q$6:$Q$105)) | E34: =IF(B34="","",SUMIF(Расчёт!$A$6:$A$105,7,Расчёт!$R$6:$R$105)) | F34: =IF(B34="","",SUMIF(Расчёт!$A$6:$A$105,7,Расчёт!$S$6:$S$105)) | H34: =IF(Ввод!$A$38="","",Ввод!$A$38) | I34: =IF(Ввод!$B$38="","",Ввод!$B$38) | J34: =IF(Ввод!$D$38="","",Ввод!$D$38)
A35: =IF(B35="","",8) | B35: =IFERROR(INDEX(Расчёт!$B$6:$B$105,MATCH(8,Расчёт!$A$6:$A$105,0)),"") | C35: =IF(B35="","",SUMIF(Расчёт!$A$6:$A$105,8,Расчёт!$P$6:$P$105)) | D35: =IF(B35="","",SUMIF(Расчёт!$A$6:$A$105,8,Расчёт!$Q$6:$Q$105)) | E35: =IF(B35="","",SUMIF(Расчёт!$A$6:$A$105,8,Расчёт!$R$6:$R$105)) | F35: =IF(B35="","",SUMIF(Расчёт!$A$6:$A$105,8,Расчёт!$S$6:$S$105)) | H35: =IF(Ввод!$A$39="","",Ввод!$A$39) | I35: =IF(Ввод!$B$39="","",Ввод!$B$39) | J35: =IF(Ввод!$D$39="","",Ввод!$D$39)
A36: =IF(B36="","",9) | B36: =IFERROR(INDEX(Расчёт!$B$6:$B$105,MATCH(9,Расчёт!$A$6:$A$105,0)),"") | C36: =IF(B36="","",SUMIF(Расчёт!$A$6:$A$105,9,Расчёт!$P$6:$P$105)) | D36: =IF(B36="","",SUMIF(Расчёт!$A$6:$A$105,9,Расчёт!$Q$6:$Q$105)) | E36: =IF(B36="","",SUMIF(Расчёт!$A$6:$A$105,9,Расчёт!$R$6:$R$105)) | F36: =IF(B36="","",SUMIF(Расчёт!$A$6:$A$105,9,Расчёт!$S$6:$S$105))
A37: =IF(B37="","",10) | B37: =IFERROR(INDEX(Расчёт!$B$6:$B$105,MATCH(10,Расчёт!$A$6:$A$105,0)),"") | C37: =IF(B37="","",SUMIF(Расчёт!$A$6:$A$105,10,Расчёт!$P$6:$P$105)) | D37: =IF(B37="","",SUMIF(Расчёт!$A$6:$A$105,10,Расчёт!$Q$6:$Q$105)) | E37: =IF(B37="","",SUMIF(Расчёт!$A$6:$A$105,10,Расчёт!$R$6:$R$105)) | F37: =IF(B37="","",SUMIF(Расчёт!$A$6:$A$105,10,Расчёт!$S$6:$S$105))
A38: =IF(B38="","",11) | B38: =IFERROR(INDEX(Расчёт!$B$6:$B$105,MATCH(11,Расчёт!$A$6:$A$105,0)),"") | C38: =IF(B38="","",SUMIF(Расчёт!$A$6:$A$105,11,Расчёт!$P$6:$P$105)) | D38: =IF(B38="","",SUMIF(Расчёт!$A$6:$A$105,11,Расчёт!$Q$6:$Q$105)) | E38: =IF(B38="","",SUMIF(Расчёт!$A$6:$A$105,11,Расчёт!$R$6:$R$105)) | F38: =IF(B38="","",SUMIF(Расчёт!$A$6:$A$105,11,Расчёт!$S$6:$S$105)) | H38: Показатель | I38: Значение | J38: Комментарий
A39: =IF(B39="","",12) | B39: =IFERROR(INDEX(Расчёт!$B$6:$B$105,MATCH(12,Расчёт!$A$6:$A$105,0)),"") | C39: =IF(B39="","",SUMIF(Расчёт!$A$6:$A$105,12,Расчёт!$P$6:$P$105)) | D39: =IF(B39="","",SUMIF(Расчёт!$A$6:$A$105,12,Расчёт!$Q$6:$Q$105)) | E39: =IF(B39="","",SUMIF(Расчёт!$A$6:$A$105,12,Расчёт!$R$6:$R$105)) | F39: =IF(B39="","",SUMIF(Расчёт!$A$6:$A$105,12,Расчёт!$S$6:$S$105)) | H39: Часы от ИИ | I39: =SUM(Расчёт!$F$6:$F$105) -> 0 | J39: До коэффициентов
A40: =IF(B40="","",13) | B40: =IFERROR(INDEX(Расчёт!$B$6:$B$105,MATCH(13,Расчёт!$A$6:$A$105,0)),"") | C40: =IF(B40="","",SUMIF(Расчёт!$A$6:$A$105,13,Расчёт!$P$6:$P$105)) | D40: =IF(B40="","",SUMIF(Расчёт!$A$6:$A$105,13,Расчёт!$Q$6:$Q$105)) | E40: =IF(B40="","",SUMIF(Расчёт!$A$6:$A$105,13,Расчёт!$R$6:$R$105)) | F40: =IF(B40="","",SUMIF(Расчёт!$A$6:$A$105,13,Расчёт!$S$6:$S$105)) | H40: Расчётные часы | I40: =SUM(Расчёт!$P$6:$P$105) -> 0 | J40: С учётом периодичности, сложности и риска
A41: =IF(B41="","",14) | B41: =IFERROR(INDEX(Расчёт!$B$6:$B$105,MATCH(14,Расчёт!$A$6:$A$105,0)),"") | C41: =IF(B41="","",SUMIF(Расчёт!$A$6:$A$105,14,Расчёт!$P$6:$P$105)) | D41: =IF(B41="","",SUMIF(Расчёт!$A$6:$A$105,14,Расчёт!$Q$6:$Q$105)) | E41: =IF(B41="","",SUMIF(Расчёт!$A$6:$A$105,14,Расчёт!$R$6:$R$105)) | F41: =IF(B41="","",SUMIF(Расчёт!$A$6:$A$105,14,Расчёт!$S$6:$S$105)) | H41: Эквивалент FTE-дней | I41: =SUM(Расчёт!$S$6:$S$105) -> 0 | J41: С учётом параллельной команды
A42: =IF(B42="","",15) | B42: =IFERROR(INDEX(Расчёт!$B$6:$B$105,MATCH(15,Расчёт!$A$6:$A$105,0)),"") | C42: =IF(B42="","",SUMIF(Расчёт!$A$6:$A$105,15,Расчёт!$P$6:$P$105)) | D42: =IF(B42="","",SUMIF(Расчёт!$A$6:$A$105,15,Расчёт!$Q$6:$Q$105)) | E42: =IF(B42="","",SUMIF(Расчёт!$A$6:$A$105,15,Расчёт!$R$6:$R$105)) | F42: =IF(B42="","",SUMIF(Расчёт!$A$6:$A$105,15,Расчёт!$S$6:$S$105)) | H42: Внешняя себестоимость | I42: =SUM('Внешние затраты'!$I$6:$I$25) -> 0 | J42: По строкам внешних затрат
A43: =IF(B43="","",16) | B43: =IFERROR(INDEX(Расчёт!$B$6:$B$105,MATCH(16,Расчёт!$A$6:$A$105,0)),"") | C43: =IF(B43="","",SUMIF(Расчёт!$A$6:$A$105,16,Расчёт!$P$6:$P$105)) | D43: =IF(B43="","",SUMIF(Расчёт!$A$6:$A$105,16,Расчёт!$Q$6:$Q$105)) | E43: =IF(B43="","",SUMIF(Расчёт!$A$6:$A$105,16,Расчёт!$R$6:$R$105)) | F43: =IF(B43="","",SUMIF(Расчёт!$A$6:$A$105,16,Расчёт!$S$6:$S$105)) | H43: Скидка | I43: =Ввод!$B$10 -> 0 | J43: Применяется к цене до НДС
A44: =IF(B44="","",17) | B44: =IFERROR(INDEX(Расчёт!$B$6:$B$105,MATCH(17,Расчёт!$A$6:$A$105,0)),"") | C44: =IF(B44="","",SUMIF(Расчёт!$A$6:$A$105,17,Расчёт!$P$6:$P$105)) | D44: =IF(B44="","",SUMIF(Расчёт!$A$6:$A$105,17,Расчёт!$Q$6:$Q$105)) | E44: =IF(B44="","",SUMIF(Расчёт!$A$6:$A$105,17,Расчёт!$R$6:$R$105)) | F44: =IF(B44="","",SUMIF(Расчёт!$A$6:$A$105,17,Расчёт!$S$6:$S$105)) | H44: НДС | I44: =Ввод!$B$9 -> 0.2 | J44: Начисляется после скидки
A45: =IF(B45="","",18) | B45: =IFERROR(INDEX(Расчёт!$B$6:$B$105,MATCH(18,Расчёт!$A$6:$A$105,0)),"") | C45: =IF(B45="","",SUMIF(Расчёт!$A$6:$A$105,18,Расчёт!$P$6:$P$105)) | D45: =IF(B45="","",SUMIF(Расчёт!$A$6:$A$105,18,Расчёт!$Q$6:$Q$105)) | E45: =IF(B45="","",SUMIF(Расчёт!$A$6:$A$105,18,Расчёт!$R$6:$R$105)) | F45: =IF(B45="","",SUMIF(Расчёт!$A$6:$A$105,18,Расчёт!$S$6:$S$105)) | H45: Главное допущение | I45: =Ввод!$B$15 -> 0 | J45: Требуется экспертная проверка
A46: =IF(B46="","",19) | B46: =IFERROR(INDEX(Расчёт!$B$6:$B$105,MATCH(19,Расчёт!$A$6:$A$105,0)),"") | C46: =IF(B46="","",SUMIF(Расчёт!$A$6:$A$105,19,Расчёт!$P$6:$P$105)) | D46: =IF(B46="","",SUMIF(Расчёт!$A$6:$A$105,19,Расчёт!$Q$6:$Q$105)) | E46: =IF(B46="","",SUMIF(Расчёт!$A$6:$A$105,19,Расчёт!$R$6:$R$105)) | F46: =IF(B46="","",SUMIF(Расчёт!$A$6:$A$105,19,Расчёт!$S$6:$S$105))
A47: =IF(B47="","",20) | B47: =IFERROR(INDEX(Расчёт!$B$6:$B$105,MATCH(20,Расчёт!$A$6:$A$105,0)),"") | C47: =IF(B47="","",SUMIF(Расчёт!$A$6:$A$105,20,Расчёт!$P$6:$P$105)) | D47: =IF(B47="","",SUMIF(Расчёт!$A$6:$A$105,20,Расчёт!$Q$6:$Q$105)) | E47: =IF(B47="","",SUMIF(Расчёт!$A$6:$A$105,20,Расчёт!$R$6:$R$105)) | F47: =IF(B47="","",SUMIF(Расчёт!$A$6:$A$105,20,Расчёт!$S$6:$S$105))
A50: Трудозатраты по ролям
A51: Код | B51: Роль | C51: Часы | D51: Цена | E51: Себестоимость | F51: Доля часов
A52: ='Справочник ролей'!$A$2 -> 6034 | B52: ='Справочник ролей'!$C$2 -> Тимлид-Архитектор ИБ | #6034 | C52: =SUMIF(Расчёт!$K$6:$K$105,A52,Расчёт!$P$6:$P$105) -> 0 | D52: =SUMIF(Расчёт!$K$6:$K$105,A52,Расчёт!$Q$6:$Q$105) -> 0 | E52: =SUMIF(Расчёт!$K$6:$K$105,A52,Расчёт!$R$6:$R$105) -> 0 | F52: =IFERROR(C52/SUM(Расчёт!$P$6:$P$105),0) -> 0
A53: ='Справочник ролей'!$A$3 -> 6035 | B53: ='Справочник ролей'!$C$3 -> Ведущий инженер ИБ | #6035 | C53: =SUMIF(Расчёт!$K$6:$K$105,A53,Расчёт!$P$6:$P$105) -> 0 | D53: =SUMIF(Расчёт!$K$6:$K$105,A53,Расчёт!$Q$6:$Q$105) -> 0 | E53: =SUMIF(Расчёт!$K$6:$K$105,A53,Расчёт!$R$6:$R$105) -> 0 | F53: =IFERROR(C53/SUM(Расчёт!$P$6:$P$105),0) -> 0
A54: ='Справочник ролей'!$A$4 -> 6036 | B54: ='Справочник ролей'!$C$4 -> Пентестер | #6036 | C54: =SUMIF(Расчёт!$K$6:$K$105,A54,Расчёт!$P$6:$P$105) -> 0 | D54: =SUMIF(Расчёт!$K$6:$K$105,A54,Расчёт!$Q$6:$Q$105) -> 0 | E54: =SUMIF(Расчёт!$K$6:$K$105,A54,Расчёт!$R$6:$R$105) -> 0 | F54: =IFERROR(C54/SUM(Расчёт!$P$6:$P$105),0) -> 0
A55: ='Справочник ролей'!$A$5 -> 6037 | B55: ='Справочник ролей'!$C$5 -> Ведущий Архитектор ИБ | #6037 | C55: =SUMIF(Расчёт!$K$6:$K$105,A55,Расчёт!$P$6:$P$105) -> 0 | D55: =SUMIF(Расчёт!$K$6:$K$105,A55,Расчёт!$Q$6:$Q$105) -> 0 | E55: =SUMIF(Расчёт!$K$6:$K$105,A55,Расчёт!$R$6:$R$105) -> 0 | F55: =IFERROR(C55/SUM(Расчёт!$P$6:$P$105),0) -> 0
A56: ='Справочник ролей'!$A$6 -> 6039 | B56: ='Справочник ролей'!$C$6 -> Архитектор ИБ | #6039 | C56: =SUMIF(Расчёт!$K$6:$K$105,A56,Расчёт!$P$6:$P$105) -> 0 | D56: =SUMIF(Расчёт!$K$6:$K$105,A56,Расчёт!$Q$6:$Q$105) -> 0 | E56: =SUMIF(Расчёт!$K$6:$K$105,A56,Расчёт!$R$6:$R$105) -> 0 | F56: =IFERROR(C56/SUM(Расчёт!$P$6:$P$105),0) -> 0
A57: ='Справочник ролей'!$A$7 -> 472 | B57: ='Справочник ролей'!$C$7 -> Руководитель дежурной смены | #472 | C57: =SUMIF(Расчёт!$K$6:$K$105,A57,Расчёт!$P$6:$P$105) -> 0 | D57: =SUMIF(Расчёт!$K$6:$K$105,A57,Расчёт!$Q$6:$Q$105) -> 0 | E57: =SUMIF(Расчёт!$K$6:$K$105,A57,Расчёт!$R$6:$R$105) -> 0 | F57: =IFERROR(C57/SUM(Расчёт!$P$6:$P$105),0) -> 0
A58: ='Справочник ролей'!$A$8 -> 473 | B58: ='Справочник ролей'!$C$8 -> Супервизор - Руководитель группы | #473 | C58: =SUMIF(Расчёт!$K$6:$K$105,A58,Расчёт!$P$6:$P$105) -> 0 | D58: =SUMIF(Расчёт!$K$6:$K$105,A58,Расчёт!$Q$6:$Q$105) -> 0 | E58: =SUMIF(Расчёт!$K$6:$K$105,A58,Расчёт!$R$6:$R$105) -> 0 | F58: =IFERROR(C58/SUM(Расчёт!$P$6:$P$105),0) -> 0
A59: ='Справочник ролей'!$A$9 -> 474 | B59: ='Справочник ролей'!$C$9 -> L1 Инженер дежурной смены | #474 | C59: =SUMIF(Расчёт!$K$6:$K$105,A59,Расчёт!$P$6:$P$105) -> 0 | D59: =SUMIF(Расчёт!$K$6:$K$105,A59,Расчёт!$Q$6:$Q$105) -> 0 | E59: =SUMIF(Расчёт!$K$6:$K$105,A59,Расчёт!$R$6:$R$105) -> 0 | F59: =IFERROR(C59/SUM(Расчёт!$P$6:$P$105),0) -> 0
A60: ='Справочник ролей'!$A$10 -> 475 | B60: ='Справочник ролей'!$C$10 -> L2 Инженер технической поддержки | #475 | C60: =SUMIF(Расчёт!$K$6:$K$105,A60,Расчёт!$P$6:$P$105) -> 0 | D60: =SUMIF(Расчёт!$K$6:$K$105,A60,Расчёт!$Q$6:$Q$105) -> 0 | E60: =SUMIF(Расчёт!$K$6:$K$105,A60,Расчёт!$R$6:$R$105) -> 0 | F60: =IFERROR(C60/SUM(Расчёт!$P$6:$P$105),0) -> 0
A61: ='Справочник ролей'!$A$11 -> 476 | B61: ='Справочник ролей'!$C$11 -> Руководитель 3 линии | #476 | C61: =SUMIF(Расчёт!$K$6:$K$105,A61,Расчёт!$P$6:$P$105) -> 0 | D61: =SUMIF(Расчёт!$K$6:$K$105,A61,Расчёт!$Q$6:$Q$105) -> 0 | E61: =SUMIF(Расчёт!$K$6:$K$105,A61,Расчёт!$R$6:$R$105) -> 0 | F61: =IFERROR(C61/SUM(Расчёт!$P$6:$P$105),0) -> 0
A62: ='Справочник ролей'!$A$12 -> 477 | B62: ='Справочник ролей'!$C$12 -> Тимлид - Руководитель группы | #477 | C62: =SUMIF(Расчёт!$K$6:$K$105,A62,Расчёт!$P$6:$P$105) -> 0 | D62: =SUMIF(Расчёт!$K$6:$K$105,A62,Расчёт!$Q$6:$Q$105) -> 0 | E62: =SUMIF(Расчёт!$K$6:$K$105,A62,Расчёт!$R$6:$R$105) -> 0 | F62: =IFERROR(C62/SUM(Расчёт!$P$6:$P$105),0) -> 0
A63: ='Справочник ролей'!$A$13 -> 478 | B63: ='Справочник ролей'!$C$13 -> L3 Сетевой инженер | #478 | C63: =SUMIF(Расчёт!$K$6:$K$105,A63,Расчёт!$P$6:$P$105) -> 0 | D63: =SUMIF(Расчёт!$K$6:$K$105,A63,Расчёт!$Q$6:$Q$105) -> 0 | E63: =SUMIF(Расчёт!$K$6:$K$105,A63,Расчёт!$R$6:$R$105) -> 0 | F63: =IFERROR(C63/SUM(Расчёт!$P$6:$P$105),0) -> 0
A64: ='Справочник ролей'!$A$14 -> 479 | B64: ='Справочник ролей'!$C$14 -> L3 Windows инженер | #479 | C64: =SUMIF(Расчёт!$K$6:$K$105,A64,Расчёт!$P$6:$P$105) -> 0 | D64: =SUMIF(Расчёт!$K$6:$K$105,A64,Расчёт!$Q$6:$Q$105) -> 0 | E64: =SUMIF(Расчёт!$K$6:$K$105,A64,Расчёт!$R$6:$R$105) -> 0 | F64: =IFERROR(C64/SUM(Расчёт!$P$6:$P$105),0) -> 0
A65: ='Справочник ролей'!$A$15 -> 480 | B65: ='Справочник ролей'!$C$15 -> L3 Архитектор | #480 | C65: =SUMIF(Расчёт!$K$6:$K$105,A65,Расчёт!$P$6:$P$105) -> 0 | D65: =SUMIF(Расчёт!$K$6:$K$105,A65,Расчёт!$Q$6:$Q$105) -> 0 | E65: =SUMIF(Расчёт!$K$6:$K$105,A65,Расчёт!$R$6:$R$105) -> 0 | F65: =IFERROR(C65/SUM(Расчёт!$P$6:$P$105),0) -> 0
A66: ='Справочник ролей'!$A$16 -> 1202 | B66: ='Справочник ролей'!$C$16 -> L3 DevOps-инженер | #1202 | C66: =SUMIF(Расчёт!$K$6:$K$105,A66,Расчёт!$P$6:$P$105) -> 0 | D66: =SUMIF(Расчёт!$K$6:$K$105,A66,Расчёт!$Q$6:$Q$105) -> 0 | E66: =SUMIF(Расчёт!$K$6:$K$105,A66,Расчёт!$R$6:$R$105) -> 0 | F66: =IFERROR(C66/SUM(Расчёт!$P$6:$P$105),0) -> 0
A67: ='Справочник ролей'!$A$17 -> 1204 | B67: ='Справочник ролей'!$C$17 -> Руководитель проектного офиса | #1204 | C67: =SUMIF(Расчёт!$K$6:$K$105,A67,Расчёт!$P$6:$P$105) -> 0 | D67: =SUMIF(Расчёт!$K$6:$K$105,A67,Расчёт!$Q$6:$Q$105) -> 0 | E67: =SUMIF(Расчёт!$K$6:$K$105,A67,Расчёт!$R$6:$R$105) -> 0 | F67: =IFERROR(C67/SUM(Расчёт!$P$6:$P$105),0) -> 0
A68: ='Справочник ролей'!$A$18 -> 1205 | B68: ='Справочник ролей'!$C$18 -> Менеджер проектов | #1205 | C68: =SUMIF(Расчёт!$K$6:$K$105,A68,Расчёт!$P$6:$P$105) -> 0 | D68: =SUMIF(Расчёт!$K$6:$K$105,A68,Расчёт!$Q$6:$Q$105) -> 0 | E68: =SUMIF(Расчёт!$K$6:$K$105,A68,Расчёт!$R$6:$R$105) -> 0 | F68: =IFERROR(C68/SUM(Расчёт!$P$6:$P$105),0) -> 0
A69: ='Справочник ролей'!$A$19 -> 1206 | B69: ='Справочник ролей'!$C$19 -> Администратор проектов | #1206 | C69: =SUMIF(Расчёт!$K$6:$K$105,A69,Расчёт!$P$6:$P$105) -> 0 | D69: =SUMIF(Расчёт!$K$6:$K$105,A69,Расчёт!$Q$6:$Q$105) -> 0 | E69: =SUMIF(Расчёт!$K$6:$K$105,A69,Расчёт!$R$6:$R$105) -> 0 | F69: =IFERROR(C69/SUM(Расчёт!$P$6:$P$105),0) -> 0
A70: ='Справочник ролей'!$A$20 -> 1207 | B70: ='Справочник ролей'!$C$20 -> L3 DBA инженер | #1207 | C70: =SUMIF(Расчёт!$K$6:$K$105,A70,Расчёт!$P$6:$P$105) -> 0 | D70: =SUMIF(Расчёт!$K$6:$K$105,A70,Расчёт!$Q$6:$Q$105) -> 0 | E70: =SUMIF(Расчёт!$K$6:$K$105,A70,Расчёт!$R$6:$R$105) -> 0 | F70: =IFERROR(C70/SUM(Расчёт!$P$6:$P$105),0) -> 0

Sheet Ввод
A1: Параметры проекта и тип расчёта
A3: Общие параметры | D3: Определяется выбранным типом
A4: Название проекта | D4: Направление | E4: =IFERROR(VLOOKUP($B$5,'Справочник типов'!$A$2:$J$27,2,FALSE),"") | F4: Код типа из ИИ можно заменить вручную. Расчёт и набор параметров обновятся автоматически.
A5: Тип проекта | D5: Продукт | E5: =IFERROR(VLOOKUP($B$5,'Справочник типов'!$A$2:$J$27,3,FALSE),"") | F5: Параметры типа проекта загружаются из справочника.
A6: Дата оценки | D6: Расчётная модель | E6: =IFERROR(VLOOKUP($B$5,'Справочник типов'!$A$2:$J$27,8,FALSE),"") | F6: Для поддержки и подписок часы «Авто» считаются ежемесячными; для внедрений и аудитов — общими.
A7: Режим оценки | B7: Бюджетная | D7: Категория | E7: =IFERROR(VLOOKUP($B$5,'Справочник типов'!$A$2:$J$27,5,FALSE),"") | F7: Строка расчёта может переопределить периодичность и ставки.
A8: Уверенность оценки | B8: 0.7 | D8: Ориентир срока, мес. | E8: =IFERROR(VLOOKUP($B$5,'Справочник типов'!$A$2:$J$27,6,FALSE),"") | F8: Внешние затраты считаются отдельно; ручная цена имеет приоритет.
A9: НДС | B9: 0.2 | D9: Тип сделки | E9: =IFERROR(VLOOKUP($B$5,'Справочник типов'!$A$2:$J$27,7,FALSE),"")
A10: Скидка | B10: 0 | D10: Базис часов | E10: =IFERROR(VLOOKUP($B$5,'Справочник типов'!$A$2:$J$27,9,FALSE),"")
A11: Рабочих часов в дне | B11: 8 | D11: Метод внешних затрат | E11: =IFERROR(VLOOKUP($B$5,'Справочник типов'!$A$2:$J$27,10,FALSE),"")
A12: Плановая дата старта | D12: Источник параметров | E12: =IF($B$5="","","Справочник типов")
A13: Интерпретация часов ИИ | B13: Авто
A14: Источник / версия ТЗ
A15: Главное допущение
A16: БФ / коммерческий резерв | B16: 0
A18: Ключевые параметры выбранного типа
A19: Слот | B19: Параметр | C19: Ед. | D19: Значение от ИИ / пользователя | E19: Принятое значение | F19: Обязателен | G19: Код влияния | H19: Логика
A20: 1 | B20: =IFERROR(INDEX('Параметры типов'!$C$2:$C$209,(MATCH($B$5,'Справочник типов'!$A$2:$A$27,0)-1)*8+$A20),"") | C20: =IFERROR(INDEX('Параметры типов'!$D$2:$D$209,(MATCH($B$5,'Справочник типов'!$A$2:$A$27,0)-1)*8+$A20),"") | E20: =IF(D20<>"",D20,IFERROR(INDEX('Параметры типов'!$E$2:$E$209,(MATCH($B$5,'Справочник типов'!$A$2:$A$27,0)-1)*8+$A20),"")) | F20: =IFERROR(INDEX('Параметры типов'!$F$2:$F$209,(MATCH($B$5,'Справочник типов'!$A$2:$A$27,0)-1)*8+$A20),"") | G20: =IFERROR(INDEX('Параметры типов'!$G$2:$G$209,(MATCH($B$5,'Справочник типов'!$A$2:$A$27,0)-1)*8+$A20),"") | H20: =IFERROR(INDEX('Параметры типов'!$H$2:$H$209,(MATCH($B$5,'Справочник типов'!$A$2:$A$27,0)-1)*8+$A20),"")
A21: 2 | B21: =IFERROR(INDEX('Параметры типов'!$C$2:$C$209,(MATCH($B$5,'Справочник типов'!$A$2:$A$27,0)-1)*8+$A21),"") | C21: =IFERROR(INDEX('Параметры типов'!$D$2:$D$209,(MATCH($B$5,'Справочник типов'!$A$2:$A$27,0)-1)*8+$A21),"") | E21: =IF(D21<>"",D21,IFERROR(INDEX('Параметры типов'!$E$2:$E$209,(MATCH($B$5,'Справочник типов'!$A$2:$A$27,0)-1)*8+$A21),"")) | F21: =IFERROR(INDEX('Параметры типов'!$F$2:$F$209,(MATCH($B$5,'Справочник типов'!$A$2:$A$27,0)-1)*8+$A21),"") | G21: =IFERROR(INDEX('Параметры типов'!$G$2:$G$209,(MATCH($B$5,'Справочник типов'!$A$2:$A$27,0)-1)*8+$A21),"") | H21: =IFERROR(INDEX('Параметры типов'!$H$2:$H$209,(MATCH($B$5,'Справочник типов'!$A$2:$A$27,0)-1)*8+$A21),"")
A22: 3 | B22: =IFERROR(INDEX('Параметры типов'!$C$2:$C$209,(MATCH($B$5,'Справочник типов'!$A$2:$A$27,0)-1)*8+$A22),"") | C22: =IFERROR(INDEX('Параметры типов'!$D$2:$D$209,(MATCH($B$5,'Справочник типов'!$A$2:$A$27,0)-1)*8+$A22),"") | E22: =IF(D22<>"",D22,IFERROR(INDEX('Параметры типов'!$E$2:$E$209,(MATCH($B$5,'Справочник типов'!$A$2:$A$27,0)-1)*8+$A22),"")) | F22: =IFERROR(INDEX('Параметры типов'!$F$2:$F$209,(MATCH($B$5,'Справочник типов'!$A$2:$A$27,0)-1)*8+$A22),"") | G22: =IFERROR(INDEX('Параметры типов'!$G$2:$G$209,(MATCH($B$5,'Справочник типов'!$A$2:$A$27,0)-1)*8+$A22),"") | H22: =IFERROR(INDEX('Параметры типов'!$H$2:$H$209,(MATCH($B$5,'Справочник типов'!$A$2:$A$27,0)-1)*8+$A22),"")
A23: 4 | B23: =IFERROR(INDEX('Параметры типов'!$C$2:$C$209,(MATCH($B$5,'Справочник типов'!$A$2:$A$27,0)-1)*8+$A23),"") | C23: =IFERROR(INDEX('Параметры типов'!$D$2:$D$209,(MATCH($B$5,'Справочник типов'!$A$2:$A$27,0)-1)*8+$A23),"") | E23: =IF(D23<>"",D23,IFERROR(INDEX('Параметры типов'!$E$2:$E$209,(MATCH($B$5,'Справочник типов'!$A$2:$A$27,0)-1)*8+$A23),"")) | F23: =IFERROR(INDEX('Параметры типов'!$F$2:$F$209,(MATCH($B$5,'Справочник типов'!$A$2:$A$27,0)-1)*8+$A23),"") | G23: =IFERROR(INDEX('Параметры типов'!$G$2:$G$209,(MATCH($B$5,'Справочник типов'!$A$2:$A$27,0)-1)*8+$A23),"") | H23: =IFERROR(INDEX('Параметры типов'!$H$2:$H$209,(MATCH($B$5,'Справочник типов'!$A$2:$A$27,0)-1)*8+$A23),"")
A24: 5 | B24: =IFERROR(INDEX('Параметры типов'!$C$2:$C$209,(MATCH($B$5,'Справочник типов'!$A$2:$A$27,0)-1)*8+$A24),"") | C24: =IFERROR(INDEX('Параметры типов'!$D$2:$D$209,(MATCH($B$5,'Справочник типов'!$A$2:$A$27,0)-1)*8+$A24),"") | E24: =IF(D24<>"",D24,IFERROR(INDEX('Параметры типов'!$E$2:$E$209,(MATCH($B$5,'Справочник типов'!$A$2:$A$27,0)-1)*8+$A24),"")) | F24: =IFERROR(INDEX('Параметры типов'!$F$2:$F$209,(MATCH($B$5,'Справочник типов'!$A$2:$A$27,0)-1)*8+$A24),"") | G24: =IFERROR(INDEX('Параметры типов'!$G$2:$G$209,(MATCH($B$5,'Справочник типов'!$A$2:$A$27,0)-1)*8+$A24),"") | H24: =IFERROR(INDEX('Параметры типов'!$H$2:$H$209,(MATCH($B$5,'Справочник типов'!$A$2:$A$27,0)-1)*8+$A24),"")
A25: 6 | B25: =IFERROR(INDEX('Параметры типов'!$C$2:$C$209,(MATCH($B$5,'Справочник типов'!$A$2:$A$27,0)-1)*8+$A25),"") | C25: =IFERROR(INDEX('Параметры типов'!$D$2:$D$209,(MATCH($B$5,'Справочник типов'!$A$2:$A$27,0)-1)*8+$A25),"") | E25: =IF(D25<>"",D25,IFERROR(INDEX('Параметры типов'!$E$2:$E$209,(MATCH($B$5,'Справочник типов'!$A$2:$A$27,0)-1)*8+$A25),"")) | F25: =IFERROR(INDEX('Параметры типов'!$F$2:$F$209,(MATCH($B$5,'Справочник типов'!$A$2:$A$27,0)-1)*8+$A25),"") | G25: =IFERROR(INDEX('Параметры типов'!$G$2:$G$209,(MATCH($B$5,'Справочник типов'!$A$2:$A$27,0)-1)*8+$A25),"") | H25: =IFERROR(INDEX('Параметры типов'!$H$2:$H$209,(MATCH($B$5,'Справочник типов'!$A$2:$A$27,0)-1)*8+$A25),"")
A26: 7 | B26: =IFERROR(INDEX('Параметры типов'!$C$2:$C$209,(MATCH($B$5,'Справочник типов'!$A$2:$A$27,0)-1)*8+$A26),"") | C26: =IFERROR(INDEX('Параметры типов'!$D$2:$D$209,(MATCH($B$5,'Справочник типов'!$A$2:$A$27,0)-1)*8+$A26),"") | E26: =IF(D26<>"",D26,IFERROR(INDEX('Параметры типов'!$E$2:$E$209,(MATCH($B$5,'Справочник типов'!$A$2:$A$27,0)-1)*8+$A26),"")) | F26: =IFERROR(INDEX('Параметры типов'!$F$2:$F$209,(MATCH($B$5,'Справочник типов'!$A$2:$A$27,0)-1)*8+$A26),"") | G26: =IFERROR(INDEX('Параметры типов'!$G$2:$G$209,(MATCH($B$5,'Справочник типов'!$A$2:$A$27,0)-1)*8+$A26),"") | H26: =IFERROR(INDEX('Параметры типов'!$H$2:$H$209,(MATCH($B$5,'Справочник типов'!$A$2:$A$27,0)-1)*8+$A26),"")
A27: 8 | B27: =IFERROR(INDEX('Параметры типов'!$C$2:$C$209,(MATCH($B$5,'Справочник типов'!$A$2:$A$27,0)-1)*8+$A27),"") | C27: =IFERROR(INDEX('Параметры типов'!$D$2:$D$209,(MATCH($B$5,'Справочник типов'!$A$2:$A$27,0)-1)*8+$A27),"") | E27: =IF(D27<>"",D27,IFERROR(INDEX('Параметры типов'!$E$2:$E$209,(MATCH($B$5,'Справочник типов'!$A$2:$A$27,0)-1)*8+$A27),"")) | F27: =IFERROR(INDEX('Параметры типов'!$F$2:$F$209,(MATCH($B$5,'Справочник типов'!$A$2:$A$27,0)-1)*8+$A27),"") | G27: =IFERROR(INDEX('Параметры типов'!$G$2:$G$209,(MATCH($B$5,'Справочник типов'!$A$2:$A$27,0)-1)*8+$A27),"") | H27: =IFERROR(INDEX('Параметры типов'!$H$2:$H$209,(MATCH($B$5,'Справочник типов'!$A$2:$A$27,0)-1)*8+$A27),"")
A30: Допущения, вопросы и ограничения
A31: Тип | B31: Формулировка | C31: Источник / основание | D31: Влияние на оценку

Sheet Расчёт
A1: Детализация этапов и работ
A3: Синие/жёлтые поля — ввод или переопределение. Формулы извлекают код роли после символа #, поэтому разделитель в названии роли не критичен.
A5: № этапа | B5: Этап | C5: № работы | D5: Работа | E5: Роль | F5: Часы ИИ | G5: База часов | H5: Кол-во (override) | I5: Ставка продажи (override) | J5: Себестоимость (override) | K5: Код роли | L5: Ставка продажи | M5: Себестоимость | N5: Принятая база | O5: Множитель | P5: Расчётные часы | Q5: Цена труда | R5: Себестоимость труда | S5: Экв. раб. дни | T5: Контроль | U5: Площадка / контур | V5: Комментарий / допущение
G6: Авто | K6: =IFERROR(MID(E6,FIND("#",E6)+1,20),"") | L6: =IF(D6="","",IF(I6<>"",I6,IFERROR(VLOOKUP(K6,'Справочник ролей'!$A$2:$E$20,4,FALSE),0))) | M6: =IF(D6="","",IF(J6<>"",J6,IFERROR(VLOOKUP(K6,'Справочник ролей'!$A$2:$E$20,5,FALSE),0))) | N6: =IF(D6="","",IF(G6<>"Авто",G6,IF(Ввод!$B$13<>"Авто",Ввод!$B$13,IFERROR(VLOOKUP(Ввод!$B$5,'Справочник типов'!$A$2:$I$27,9,FALSE),"Всего")))) | O6: =IF(D6="","",IF(N6="В месяц",MAX(1,SUMIF(Ввод!$G$20:$G$27,"TERM_MONTHS",Ввод!$E$20:$E$27)),IF(N6="На единицу",IF(H6<>"",H6,MAX(1,SUMIF(Ввод!$G$20:$G$27,"QTY",Ввод!$E$20:$E$27))),IF(N6="Ед. × месяц",IF(H6<>"",H6,MAX(1,SUMIF(Ввод!$G$20:$G$27,"QTY",Ввод!$E$20:$E$27)))*MAX(1,SUMIF(Ввод!$G$20:$G$27,"TERM_MONTHS",Ввод!$E$20:$E$27)),1)))) | P6: =IF(D6="","",F6*O6*IF(SUMIF(Ввод!$G$20:$G$27,"COMPLEXITY",Ввод!$E$20:$E$27)=0,1,SUMIF(Ввод!$G$20:$G$27,"COMPLEXITY",Ввод!$E$20:$E$27))*(1+SUMIF(Ввод!$G$20:$G$27,"RISK_PCT",Ввод!$E$20:$E$27))) | Q6: =IF(D6="","",P6*L6) | R6: =IF(D6="","",P6*M6) | S6: =IF(D6="","",P6/(Ввод!$B$11*IF(SUMIF(Ввод!$G$20:$G$27,"PARALLEL_FTE",Ввод!$E$20:$E$27)=0,1,SUMIF(Ввод!$G$20:$G$27,"PARALLEL_FTE",Ввод!$E$20:$E$27)))) | T6: =IF(D6="","",IF(F6<=0,"ПРОВЕРИТЬ ЧАСЫ",IF(AND(L6=0,M6=0),"ПРОВЕРИТЬ СТАВКУ","OK")))
G7: Авто | K7: =IFERROR(MID(E7,FIND("#",E7)+1,20),"") | L7: =IF(D7="","",IF(I7<>"",I7,IFERROR(VLOOKUP(K7,'Справочник ролей'!$A$2:$E$20,4,FALSE),0))) | M7: =IF(D7="","",IF(J7<>"",J7,IFERROR(VLOOKUP(K7,'Справочник ролей'!$A$2:$E$20,5,FALSE),0))) | N7: =IF(D7="","",IF(G7<>"Авто",G7,IF(Ввод!$B$13<>"Авто",Ввод!$B$13,IFERROR(VLOOKUP(Ввод!$B$5,'Справочник типов'!$A$2:$I$27,9,FALSE),"Всего")))) | O7: =IF(D7="","",IF(N7="В месяц",MAX(1,SUMIF(Ввод!$G$20:$G$27,"TERM_MONTHS",Ввод!$E$20:$E$27)),IF(N7="На единицу",IF(H7<>"",H7,MAX(1,SUMIF(Ввод!$G$20:$G$27,"QTY",Ввод!$E$20:$E$27))),IF(N7="Ед. × месяц",IF(H7<>"",H7,MAX(1,SUMIF(Ввод!$G$20:$G$27,"QTY",Ввод!$E$20:$E$27)))*MAX(1,SUMIF(Ввод!$G$20:$G$27,"TERM_MONTHS",Ввод!$E$20:$E$27)),1)))) | P7: =IF(D7="","",F7*O7*IF(SUMIF(Ввод!$G$20:$G$27,"COMPLEXITY",Ввод!$E$20:$E$27)=0,1,SUMIF(Ввод!$G$20:$G$27,"COMPLEXITY",Ввод!$E$20:$E$27))*(1+SUMIF(Ввод!$G$20:$G$27,"RISK_PCT",Ввод!$E$20:$E$27))) | Q7: =IF(D7="","",P7*L7) | R7: =IF(D7="","",P7*M7) | S7: =IF(D7="","",P7/(Ввод!$B$11*IF(SUMIF(Ввод!$G$20:$G$27,"PARALLEL_FTE",Ввод!$E$20:$E$27)=0,1,SUMIF(Ввод!$G$20:$G$27,"PARALLEL_FTE",Ввод!$E$20:$E$27)))) | T7: =IF(D7="","",IF(F7<=0,"ПРОВЕРИТЬ ЧАСЫ",IF(AND(L7=0,M7=0),"ПРОВЕРИТЬ СТАВКУ","OK")))
G8: Авто | K8: =IFERROR(MID(E8,FIND("#",E8)+1,20),"") | L8: =IF(D8="","",IF(I8<>"",I8,IFERROR(VLOOKUP(K8,'Справочник ролей'!$A$2:$E$20,4,FALSE),0))) | M8: =IF(D8="","",IF(J8<>"",J8,IFERROR(VLOOKUP(K8,'Справочник ролей'!$A$2:$E$20,5,FALSE),0))) | N8: =IF(D8="","",IF(G8<>"Авто",G8,IF(Ввод!$B$13<>"Авто",Ввод!$B$13,IFERROR(VLOOKUP(Ввод!$B$5,'Справочник типов'!$A$2:$I$27,9,FALSE),"Всего")))) | O8: =IF(D8="","",IF(N8="В месяц",MAX(1,SUMIF(Ввод!$G$20:$G$27,"TERM_MONTHS",Ввод!$E$20:$E$27)),IF(N8="На единицу",IF(H8<>"",H8,MAX(1,SUMIF(Ввод!$G$20:$G$27,"QTY",Ввод!$E$20:$E$27))),IF(N8="Ед. × месяц",IF(H8<>"",H8,MAX(1,SUMIF(Ввод!$G$20:$G$27,"QTY",Ввод!$E$20:$E$27)))*MAX(1,SUMIF(Ввод!$G$20:$G$27,"TERM_MONTHS",Ввод!$E$20:$E$27)),1)))) | P8: =IF(D8="","",F8*O8*IF(SUMIF(Ввод!$G$20:$G$27,"COMPLEXITY",Ввод!$E$20:$E$27)=0,1,SUMIF(Ввод!$G$20:$G$27,"COMPLEXITY",Ввод!$E$20:$E$27))*(1+SUMIF(Ввод!$G$20:$G$27,"RISK_PCT",Ввод!$E$20:$E$27))) | Q8: =IF(D8="","",P8*L8) | R8: =IF(D8="","",P8*M8) | S8: =IF(D8="","",P8/(Ввод!$B$11*IF(SUMIF(Ввод!$G$20:$G$27,"PARALLEL_FTE",Ввод!$E$20:$E$27)=0,1,SUMIF(Ввод!$G$20:$G$27,"PARALLEL_FTE",Ввод!$E$20:$E$27)))) | T8: =IF(D8="","",IF(F8<=0,"ПРОВЕРИТЬ ЧАСЫ",IF(AND(L8=0,M8=0),"ПРОВЕРИТЬ СТАВКУ","OK")))
G9: Авто | K9: =IFERROR(MID(E9,FIND("#",E9)+1,20),"") | L9: =IF(D9="","",IF(I9<>"",I9,IFERROR(VLOOKUP(K9,'Справочник ролей'!$A$2:$E$20,4,FALSE),0))) | M9: =IF(D9="","",IF(J9<>"",J9,IFERROR(VLOOKUP(K9,'Справочник ролей'!$A$2:$E$20,5,FALSE),0))) | N9: =IF(D9="","",IF(G9<>"Авто",G9,IF(Ввод!$B$13<>"Авто",Ввод!$B$13,IFERROR(VLOOKUP(Ввод!$B$5,'Справочник типов'!$A$2:$I$27,9,FALSE),"Всего")))) | O9: =IF(D9="","",IF(N9="В месяц",MAX(1,SUMIF(Ввод!$G$20:$G$27,"TERM_MONTHS",Ввод!$E$20:$E$27)),IF(N9="На единицу",IF(H9<>"",H9,MAX(1,SUMIF(Ввод!$G$20:$G$27,"QTY",Ввод!$E$20:$E$27))),IF(N9="Ед. × месяц",IF(H9<>"",H9,MAX(1,SUMIF(Ввод!$G$20:$G$27,"QTY",Ввод!$E$20:$E$27)))*MAX(1,SUMIF(Ввод!$G$20:$G$27,"TERM_MONTHS",Ввод!$E$20:$E$27)),1)))) | P9: =IF(D9="","",F9*O9*IF(SUMIF(Ввод!$G$20:$G$27,"COMPLEXITY",Ввод!$E$20:$E$27)=0,1,SUMIF(Ввод!$G$20:$G$27,"COMPLEXITY",Ввод!$E$20:$E$27))*(1+SUMIF(Ввод!$G$20:$G$27,"RISK_PCT",Ввод!$E$20:$E$27))) | Q9: =IF(D9="","",P9*L9) | R9: =IF(D9="","",P9*M9) | S9: =IF(D9="","",P9/(Ввод!$B$11*IF(SUMIF(Ввод!$G$20:$G$27,"PARALLEL_FTE",Ввод!$E$20:$E$27)=0,1,SUMIF(Ввод!$G$20:$G$27,"PARALLEL_FTE",Ввод!$E$20:$E$27)))) | T9: =IF(D9="","",IF(F9<=0,"ПРОВЕРИТЬ ЧАСЫ",IF(AND(L9=0,M9=0),"ПРОВЕРИТЬ СТАВКУ","OK")))
G10: Авто | K10: =IFERROR(MID(E10,FIND("#",E10)+1,20),"") | L10: =IF(D10="","",IF(I10<>"",I10,IFERROR(VLOOKUP(K10,'Справочник ролей'!$A$2:$E$20,4,FALSE),0))) | M10: =IF(D10="","",IF(J10<>"",J10,IFERROR(VLOOKUP(K10,'Справочник ролей'!$A$2:$E$20,5,FALSE),0))) | N10: =IF(D10="","",IF(G10<>"Авто",G10,IF(Ввод!$B$13<>"Авто",Ввод!$B$13,IFERROR(VLOOKUP(Ввод!$B$5,'Справочник типов'!$A$2:$I$27,9,FALSE),"Всего")))) | O10: =IF(D10="","",IF(N10="В месяц",MAX(1,SUMIF(Ввод!$G$20:$G$27,"TERM_MONTHS",Ввод!$E$20:$E$27)),IF(N10="На единицу",IF(H10<>"",H10,MAX(1,SUMIF(Ввод!$G$20:$G$27,"QTY",Ввод!$E$20:$E$27))),IF(N10="Ед. × месяц",IF(H10<>"",H10,MAX(1,SUMIF(Ввод!$G$20:$G$27,"QTY",Ввод!$E$20:$E$27)))*MAX(1,SUMIF(Ввод!$G$20:$G$27,"TERM_MONTHS",Ввод!$E$20:$E$27)),1)))) | P10: =IF(D10="","",F10*O10*IF(SUMIF(Ввод!$G$20:$G$27,"COMPLEXITY",Ввод!$E$20:$E$27)=0,1,SUMIF(Ввод!$G$20:$G$27,"COMPLEXITY",Ввод!$E$20:$E$27))*(1+SUMIF(Ввод!$G$20:$G$27,"RISK_PCT",Ввод!$E$20:$E$27))) | Q10: =IF(D10="","",P10*L10) | R10: =IF(D10="","",P10*M10) | S10: =IF(D10="","",P10/(Ввод!$B$11*IF(SUMIF(Ввод!$G$20:$G$27,"PARALLEL_FTE",Ввод!$E$20:$E$27)=0,1,SUMIF(Ввод!$G$20:$G$27,"PARALLEL_FTE",Ввод!$E$20:$E$27)))) | T10: =IF(D10="","",IF(F10<=0,"ПРОВЕРИТЬ ЧАСЫ",IF(AND(L10=0,M10=0),"ПРОВЕРИТЬ СТАВКУ","OK")))
G11: Авто | K11: =IFERROR(MID(E11,FIND("#",E11)+1,20),"") | L11: =IF(D11="","",IF(I11<>"",I11,IFERROR(VLOOKUP(K11,'Справочник ролей'!$A$2:$E$20,4,FALSE),0))) | M11: =IF(D11="","",IF(J11<>"",J11,IFERROR(VLOOKUP(K11,'Справочник ролей'!$A$2:$E$20,5,FALSE),0))) | N11: =IF(D11="","",IF(G11<>"Авто",G11,IF(Ввод!$B$13<>"Авто",Ввод!$B$13,IFERROR(VLOOKUP(Ввод!$B$5,'Справочник типов'!$A$2:$I$27,9,FALSE),"Всего")))) | O11: =IF(D11="","",IF(N11="В месяц",MAX(1,SUMIF(Ввод!$G$20:$G$27,"TERM_MONTHS",Ввод!$E$20:$E$27)),IF(N11="На единицу",IF(H11<>"",H11,MAX(1,SUMIF(Ввод!$G$20:$G$27,"QTY",Ввод!$E$20:$E$27))),IF(N11="Ед. × месяц",IF(H11<>"",H11,MAX(1,SUMIF(Ввод!$G$20:$G$27,"QTY",Ввод!$E$20:$E$27)))*MAX(1,SUMIF(Ввод!$G$20:$G$27,"TERM_MONTHS",Ввод!$E$20:$E$27)),1)))) | P11: =IF(D11="","",F11*O11*IF(SUMIF(Ввод!$G$20:$G$27,"COMPLEXITY",Ввод!$E$20:$E$27)=0,1,SUMIF(Ввод!$G$20:$G$27,"COMPLEXITY",Ввод!$E$20:$E$27))*(1+SUMIF(Ввод!$G$20:$G$27,"RISK_PCT",Ввод!$E$20:$E$27))) | Q11: =IF(D11="","",P11*L11) | R11: =IF(D11="","",P11*M11) | S11: =IF(D11="","",P11/(Ввод!$B$11*IF(SUMIF(Ввод!$G$20:$G$27,"PARALLEL_FTE",Ввод!$E$20:$E$27)=0,1,SUMIF(Ввод!$G$20:$G$27,"PARALLEL_FTE",Ввод!$E$20:$E$27)))) | T11: =IF(D11="","",IF(F11<=0,"ПРОВЕРИТЬ ЧАСЫ",IF(AND(L11=0,M11=0),"ПРОВЕРИТЬ СТАВКУ","OK")))
G12: Авто | K12: =IFERROR(MID(E12,FIND("#",E12)+1,20),"") | L12: =IF(D12="","",IF(I12<>"",I12,IFERROR(VLOOKUP(K12,'Справочник ролей'!$A$2:$E$20,4,FALSE),0))) | M12: =IF(D12="","",IF(J12<>"",J12,IFERROR(VLOOKUP(K12,'Справочник ролей'!$A$2:$E$20,5,FALSE),0))) | N12: =IF(D12="","",IF(G12<>"Авто",G12,IF(Ввод!$B$13<>"Авто",Ввод!$B$13,IFERROR(VLOOKUP(Ввод!$B$5,'Справочник типов'!$A$2:$I$27,9,FALSE),"Всего")))) | O12: =IF(D12="","",IF(N12="В месяц",MAX(1,SUMIF(Ввод!$G$20:$G$27,"TERM_MONTHS",Ввод!$E$20:$E$27)),IF(N12="На единицу",IF(H12<>"",H12,MAX(1,SUMIF(Ввод!$G$20:$G$27,"QTY",Ввод!$E$20:$E$27))),IF(N12="Ед. × месяц",IF(H12<>"",H12,MAX(1,SUMIF(Ввод!$G$20:$G$27,"QTY",Ввод!$E$20:$E$27)))*MAX(1,SUMIF(Ввод!$G$20:$G$27,"TERM_MONTHS",Ввод!$E$20:$E$27)),1)))) | P12: =IF(D12="","",F12*O12*IF(SUMIF(Ввод!$G$20:$G$27,"COMPLEXITY",Ввод!$E$20:$E$27)=0,1,SUMIF(Ввод!$G$20:$G$27,"COMPLEXITY",Ввод!$E$20:$E$27))*(1+SUMIF(Ввод!$G$20:$G$27,"RISK_PCT",Ввод!$E$20:$E$27))) | Q12: =IF(D12="","",P12*L12) | R12: =IF(D12="","",P12*M12) | S12: =IF(D12="","",P12/(Ввод!$B$11*IF(SUMIF(Ввод!$G$20:$G$27,"PARALLEL_FTE",Ввод!$E$20:$E$27)=0,1,SUMIF(Ввод!$G$20:$G$27,"PARALLEL_FTE",Ввод!$E$20:$E$27)))) | T12: =IF(D12="","",IF(F12<=0,"ПРОВЕРИТЬ ЧАСЫ",IF(AND(L12=0,M12=0),"ПРОВЕРИТЬ СТАВКУ","OK")))
G13: Авто | K13: =IFERROR(MID(E13,FIND("#",E13)+1,20),"") | L13: =IF(D13="","",IF(I13<>"",I13,IFERROR(VLOOKUP(K13,'Справочник ролей'!$A$2:$E$20,4,FALSE),0))) | M13: =IF(D13="","",IF(J13<>"",J13,IFERROR(VLOOKUP(K13,'Справочник ролей'!$A$2:$E$20,5,FALSE),0))) | N13: =IF(D13="","",IF(G13<>"Авто",G13,IF(Ввод!$B$13<>"Авто",Ввод!$B$13,IFERROR(VLOOKUP(Ввод!$B$5,'Справочник типов'!$A$2:$I$27,9,FALSE),"Всего")))) | O13: =IF(D13="","",IF(N13="В месяц",MAX(1,SUMIF(Ввод!$G$20:$G$27,"TERM_MONTHS",Ввод!$E$20:$E$27)),IF(N13="На единицу",IF(H13<>"",H13,MAX(1,SUMIF(Ввод!$G$20:$G$27,"QTY",Ввод!$E$20:$E$27))),IF(N13="Ед. × месяц",IF(H13<>"",H13,MAX(1,SUMIF(Ввод!$G$20:$G$27,"QTY",Ввод!$E$20:$E$27)))*MAX(1,SUMIF(Ввод!$G$20:$G$27,"TERM_MONTHS",Ввод!$E$20:$E$27)),1)))) | P13: =IF(D13="","",F13*O13*IF(SUMIF(Ввод!$G$20:$G$27,"COMPLEXITY",Ввод!$E$20:$E$27)=0,1,SUMIF(Ввод!$G$20:$G$27,"COMPLEXITY",Ввод!$E$20:$E$27))*(1+SUMIF(Ввод!$G$20:$G$27,"RISK_PCT",Ввод!$E$20:$E$27))) | Q13: =IF(D13="","",P13*L13) | R13: =IF(D13="","",P13*M13) | S13: =IF(D13="","",P13/(Ввод!$B$11*IF(SUMIF(Ввод!$G$20:$G$27,"PARALLEL_FTE",Ввод!$E$20:$E$27)=0,1,SUMIF(Ввод!$G$20:$G$27,"PARALLEL_FTE",Ввод!$E$20:$E$27)))) | T13: =IF(D13="","",IF(F13<=0,"ПРОВЕРИТЬ ЧАСЫ",IF(AND(L13=0,M13=0),"ПРОВЕРИТЬ СТАВКУ","OK")))
G14: Авто | K14: =IFERROR(MID(E14,FIND("#",E14)+1,20),"") | L14: =IF(D14="","",IF(I14<>"",I14,IFERROR(VLOOKUP(K14,'Справочник ролей'!$A$2:$E$20,4,FALSE),0))) | M14: =IF(D14="","",IF(J14<>"",J14,IFERROR(VLOOKUP(K14,'Справочник ролей'!$A$2:$E$20,5,FALSE),0))) | N14: =IF(D14="","",IF(G14<>"Авто",G14,IF(Ввод!$B$13<>"Авто",Ввод!$B$13,IFERROR(VLOOKUP(Ввод!$B$5,'Справочник типов'!$A$2:$I$27,9,FALSE),"Всего")))) | O14: =IF(D14="","",IF(N14="В месяц",MAX(1,SUMIF(Ввод!$G$20:$G$27,"TERM_MONTHS",Ввод!$E$20:$E$27)),IF(N14="На единицу",IF(H14<>"",H14,MAX(1,SUMIF(Ввод!$G$20:$G$27,"QTY",Ввод!$E$20:$E$27))),IF(N14="Ед. × месяц",IF(H14<>"",H14,MAX(1,SUMIF(Ввод!$G$20:$G$27,"QTY",Ввод!$E$20:$E$27)))*MAX(1,SUMIF(Ввод!$G$20:$G$27,"TERM_MONTHS",Ввод!$E$20:$E$27)),1)))) | P14: =IF(D14="","",F14*O14*IF(SUMIF(Ввод!$G$20:$G$27,"COMPLEXITY",Ввод!$E$20:$E$27)=0,1,SUMIF(Ввод!$G$20:$G$27,"COMPLEXITY",Ввод!$E$20:$E$27))*(1+SUMIF(Ввод!$G$20:$G$27,"RISK_PCT",Ввод!$E$20:$E$27))) | Q14: =IF(D14="","",P14*L14) | R14: =IF(D14="","",P14*M14) | S14: =IF(D14="","",P14/(Ввод!$B$11*IF(SUMIF(Ввод!$G$20:$G$27,"PARALLEL_FTE",Ввод!$E$20:$E$27)=0,1,SUMIF(Ввод!$G$20:$G$27,"PARALLEL_FTE",Ввод!$E$20:$E$27)))) | T14: =IF(D14="","",IF(F14<=0,"ПРОВЕРИТЬ ЧАСЫ",IF(AND(L14=0,M14=0),"ПРОВЕРИТЬ СТАВКУ","OK")))
G15: Авто | K15: =IFERROR(MID(E15,FIND("#",E15)+1,20),"") | L15: =IF(D15="","",IF(I15<>"",I15,IFERROR(VLOOKUP(K15,'Справочник ролей'!$A$2:$E$20,4,FALSE),0))) | M15: =IF(D15="","",IF(J15<>"",J15,IFERROR(VLOOKUP(K15,'Справочник ролей'!$A$2:$E$20,5,FALSE),0))) | N15: =IF(D15="","",IF(G15<>"Авто",G15,IF(Ввод!$B$13<>"Авто",Ввод!$B$13,IFERROR(VLOOKUP(Ввод!$B$5,'Справочник типов'!$A$2:$I$27,9,FALSE),"Всего")))) | O15: =IF(D15="","",IF(N15="В месяц",MAX(1,SUMIF(Ввод!$G$20:$G$27,"TERM_MONTHS",Ввод!$E$20:$E$27)),IF(N15="На единицу",IF(H15<>"",H15,MAX(1,SUMIF(Ввод!$G$20:$G$27,"QTY",Ввод!$E$20:$E$27))),IF(N15="Ед. × месяц",IF(H15<>"",H15,MAX(1,SUMIF(Ввод!$G$20:$G$27,"QTY",Ввод!$E$20:$E$27)))*MAX(1,SUMIF(Ввод!$G$20:$G$27,"TERM_MONTHS",Ввод!$E$20:$E$27)),1)))) | P15: =IF(D15="","",F15*O15*IF(SUMIF(Ввод!$G$20:$G$27,"COMPLEXITY",Ввод!$E$20:$E$27)=0,1,SUMIF(Ввод!$G$20:$G$27,"COMPLEXITY",Ввод!$E$20:$E$27))*(1+SUMIF(Ввод!$G$20:$G$27,"RISK_PCT",Ввод!$E$20:$E$27))) | Q15: =IF(D15="","",P15*L15) | R15: =IF(D15="","",P15*M15) | S15: =IF(D15="","",P15/(Ввод!$B$11*IF(SUMIF(Ввод!$G$20:$G$27,"PARALLEL_FTE",Ввод!$E$20:$E$27)=0,1,SUMIF(Ввод!$G$20:$G$27,"PARALLEL_FTE",Ввод!$E$20:$E$27)))) | T15: =IF(D15="","",IF(F15<=0,"ПРОВЕРИТЬ ЧАСЫ",IF(AND(L15=0,M15=0),"ПРОВЕРИТЬ СТАВКУ","OK")))
G16: Авто | K16: =IFERROR(MID(E16,FIND("#",E16)+1,20),"") | L16: =IF(D16="","",IF(I16<>"",I16,IFERROR(VLOOKUP(K16,'Справочник ролей'!$A$2:$E$20,4,FALSE),0))) | M16: =IF(D16="","",IF(J16<>"",J16,IFERROR(VLOOKUP(K16,'Справочник ролей'!$A$2:$E$20,5,FALSE),0))) | N16: =IF(D16="","",IF(G16<>"Авто",G16,IF(Ввод!$B$13<>"Авто",Ввод!$B$13,IFERROR(VLOOKUP(Ввод!$B$5,'Справочник типов'!$A$2:$I$27,9,FALSE),"Всего")))) | O16: =IF(D16="","",IF(N16="В месяц",MAX(1,SUMIF(Ввод!$G$20:$G$27,"TERM_MONTHS",Ввод!$E$20:$E$27)),IF(N16="На единицу",IF(H16<>"",H16,MAX(1,SUMIF(Ввод!$G$20:$G$27,"QTY",Ввод!$E$20:$E$27))),IF(N16="Ед. × месяц",IF(H16<>"",H16,MAX(1,SUMIF(Ввод!$G$20:$G$27,"QTY",Ввод!$E$20:$E$27)))*MAX(1,SUMIF(Ввод!$G$20:$G$27,"TERM_MONTHS",Ввод!$E$20:$E$27)),1)))) | P16: =IF(D16="","",F16*O16*IF(SUMIF(Ввод!$G$20:$G$27,"COMPLEXITY",Ввод!$E$20:$E$27)=0,1,SUMIF(Ввод!$G$20:$G$27,"COMPLEXITY",Ввод!$E$20:$E$27))*(1+SUMIF(Ввод!$G$20:$G$27,"RISK_PCT",Ввод!$E$20:$E$27))) | Q16: =IF(D16="","",P16*L16) | R16: =IF(D16="","",P16*M16) | S16: =IF(D16="","",P16/(Ввод!$B$11*IF(SUMIF(Ввод!$G$20:$G$27,"PARALLEL_FTE",Ввод!$E$20:$E$27)=0,1,SUMIF(Ввод!$G$20:$G$27,"PARALLEL_FTE",Ввод!$E$20:$E$27)))) | T16: =IF(D16="","",IF(F16<=0,"ПРОВЕРИТЬ ЧАСЫ",IF(AND(L16=0,M16=0),"ПРОВЕРИТЬ СТАВКУ","OK")))
G17: Авто | K17: =IFERROR(MID(E17,FIND("#",E17)+1,20),"") | L17: =IF(D17="","",IF(I17<>"",I17,IFERROR(VLOOKUP(K17,'Справочник ролей'!$A$2:$E$20,4,FALSE),0))) | M17: =IF(D17="","",IF(J17<>"",J17,IFERROR(VLOOKUP(K17,'Справочник ролей'!$A$2:$E$20,5,FALSE),0))) | N17: =IF(D17="","",IF(G17<>"Авто",G17,IF(Ввод!$B$13<>"Авто",Ввод!$B$13,IFERROR(VLOOKUP(Ввод!$B$5,'Справочник типов'!$A$2:$I$27,9,FALSE),"Всего")))) | O17: =IF(D17="","",IF(N17="В месяц",MAX(1,SUMIF(Ввод!$G$20:$G$27,"TERM_MONTHS",Ввод!$E$20:$E$27)),IF(N17="На единицу",IF(H17<>"",H17,MAX(1,SUMIF(Ввод!$G$20:$G$27,"QTY",Ввод!$E$20:$E$27))),IF(N17="Ед. × месяц",IF(H17<>"",H17,MAX(1,SUMIF(Ввод!$G$20:$G$27,"QTY",Ввод!$E$20:$E$27)))*MAX(1,SUMIF(Ввод!$G$20:$G$27,"TERM_MONTHS",Ввод!$E$20:$E$27)),1)))) | P17: =IF(D17="","",F17*O17*IF(SUMIF(Ввод!$G$20:$G$27,"COMPLEXITY",Ввод!$E$20:$E$27)=0,1,SUMIF(Ввод!$G$20:$G$27,"COMPLEXITY",Ввод!$E$20:$E$27))*(1+SUMIF(Ввод!$G$20:$G$27,"RISK_PCT",Ввод!$E$20:$E$27))) | Q17: =IF(D17="","",P17*L17) | R17: =IF(D17="","",P17*M17) | S17: =IF(D17="","",P17/(Ввод!$B$11*IF(SUMIF(Ввод!$G$20:$G$27,"PARALLEL_FTE",Ввод!$E$20:$E$27)=0,1,SUMIF(Ввод!$G$20:$G$27,"PARALLEL_FTE",Ввод!$E$20:$E$27)))) | T17: =IF(D17="","",IF(F17<=0,"ПРОВЕРИТЬ ЧАСЫ",IF(AND(L17=0,M17=0),"ПРОВЕРИТЬ СТАВКУ","OK")))
... G105: Авто | K105: =IFERROR(MID(E105,FIND("#",E105)+1,20),"") | L105: =IF(D105="","",IF(I105<>"",I105,IFERROR(VLOOKUP(K105,'Справочник ролей'!$A$2:$E$20,4,FALSE),0))) | M105: =IF(D105="","",IF(J105<>"",J105,IFERROR(VLOOKUP(K105,'Справочник ролей'!$A$2:$E$20,5,FALSE),0))) | N105: =IF(D105="","",IF(G105<>"Авто",G105,IF(Ввод!$B$13<>"Авто",Ввод!$B$13,IFERROR(VLOOKUP(Ввод!$B$5,'Справочник типов'!$A$2:$I$27,9,FALSE),"Всего")))) | O105: =IF(D105="","",IF(N105="В месяц",MAX(1,SUMIF(Ввод!$G$20:$G$27,"TERM_MONTHS",Ввод!$E$20:$E$27)),IF(N105="На единицу",IF(H105<>"",H105,MAX(1,SUMIF(Ввод!$G$20:$G$27,"QTY",Ввод!$E$20:$E$27))),IF(N105="Ед. × месяц",IF(H105<>"",H105,MAX(1,SUMIF(Ввод!$G$20:$G$27,"QTY",Ввод!$E$20:$E$27)))*MAX(1,SUMIF(Ввод!$G$20:$G$27,"TERM_MONTHS",Ввод!$E$20:$E$27)),1)))) | P105: =IF(D105="","",F105*O105*IF(SUMIF(Ввод!$G$20:$G$27,"COMPLEXITY",Ввод!$E$20:$E$27)=0,1,SUMIF(Ввод!$G$20:$G$27,"COMPLEXITY",Ввод!$E$20:$E$27))*(1+SUMIF(Ввод!$G$20:$G$27,"RISK_PCT",Ввод!$E$20:$E$27))) | Q105: =IF(D105="","",P105*L105) | R105: =IF(D105="","",P105*M105) | S105: =IF(D105="","",P105/(Ввод!$B$11*IF(SUMIF(Ввод!$G$20:$G$27,"PARALLEL_FTE",Ввод!$E$20:$E$27)=0,1,SUMIF(Ввод!$G$20:$G$27,"PARALLEL_FTE",Ввод!$E$20:$E$27)))) | T105: =IF(D105="","",IF(F105<=0,"ПРОВЕРИТЬ ЧАСЫ",IF(AND(L105=0,M105=0),"ПРОВЕРИТЬ СТАВКУ","OK")))

Sheet Внешние затраты
A1: Провайдеры, лицензии, оборудование и прочие расходы
A3: Если цена продажи за единицу заполнена, она имеет приоритет. Иначе применяется метод выбранного типа: маржа или наценка. Для ежемесячных строк применяется срок договора.
A5: Категория | B5: Описание | C5: Количество | D5: Ед. | E5: Себестоимость за ед. | F5: Цена продажи за ед. (ручная) | G5: Периодичность | H5: Множитель | I5: Итого себестоимость | J5: Итого цена | K5: Комментарий
G6: Разово | H6: =IF(B6="","",IF(G6="В месяц",MAX(1,SUMIF(Ввод!$G$20:$G$27,"TERM_MONTHS",Ввод!$E$20:$E$27)),1)) | I6: =IF(B6="","",C6*E6*H6) | J6: =IF(B6="","",IF(F6<>"",C6*F6*H6,IF(IFERROR(VLOOKUP(Ввод!$B$5,'Справочник типов'!$A$2:$J$27,10,FALSE),"По наценке")="По марже",IF(SUMIF(Ввод!$G$20:$G$27,"TARGET_MARGIN",Ввод!$E$20:$E$27)<1,I6/(1-SUMIF(Ввод!$G$20:$G$27,"TARGET_MARGIN",Ввод!$E$20:$E$27)),0),I6*(1+SUMIF(Ввод!$G$20:$G$27,"MARKUP",Ввод!$E$20:$E$27)))))
G7: Разово | H7: =IF(B7="","",IF(G7="В месяц",MAX(1,SUMIF(Ввод!$G$20:$G$27,"TERM_MONTHS",Ввод!$E$20:$E$27)),1)) | I7: =IF(B7="","",C7*E7*H7) | J7: =IF(B7="","",IF(F7<>"",C7*F7*H7,IF(IFERROR(VLOOKUP(Ввод!$B$5,'Справочник типов'!$A$2:$J$27,10,FALSE),"По наценке")="По марже",IF(SUMIF(Ввод!$G$20:$G$27,"TARGET_MARGIN",Ввод!$E$20:$E$27)<1,I7/(1-SUMIF(Ввод!$G$20:$G$27,"TARGET_MARGIN",Ввод!$E$20:$E$27)),0),I7*(1+SUMIF(Ввод!$G$20:$G$27,"MARKUP",Ввод!$E$20:$E$27)))))
G8: Разово | H8: =IF(B8="","",IF(G8="В месяц",MAX(1,SUMIF(Ввод!$G$20:$G$27,"TERM_MONTHS",Ввод!$E$20:$E$27)),1)) | I8: =IF(B8="","",C8*E8*H8) | J8: =IF(B8="","",IF(F8<>"",C8*F8*H8,IF(IFERROR(VLOOKUP(Ввод!$B$5,'Справочник типов'!$A$2:$J$27,10,FALSE),"По наценке")="По марже",IF(SUMIF(Ввод!$G$20:$G$27,"TARGET_MARGIN",Ввод!$E$20:$E$27)<1,I8/(1-SUMIF(Ввод!$G$20:$G$27,"TARGET_MARGIN",Ввод!$E$20:$E$27)),0),I8*(1+SUMIF(Ввод!$G$20:$G$27,"MARKUP",Ввод!$E$20:$E$27)))))
G9: Разово | H9: =IF(B9="","",IF(G9="В месяц",MAX(1,SUMIF(Ввод!$G$20:$G$27,"TERM_MONTHS",Ввод!$E$20:$E$27)),1)) | I9: =IF(B9="","",C9*E9*H9) | J9: =IF(B9="","",IF(F9<>"",C9*F9*H9,IF(IFERROR(VLOOKUP(Ввод!$B$5,'Справочник типов'!$A$2:$J$27,10,FALSE),"По наценке")="По марже",IF(SUMIF(Ввод!$G$20:$G$27,"TARGET_MARGIN",Ввод!$E$20:$E$27)<1,I9/(1-SUMIF(Ввод!$G$20:$G$27,"TARGET_MARGIN",Ввод!$E$20:$E$27)),0),I9*(1+SUMIF(Ввод!$G$20:$G$27,"MARKUP",Ввод!$E$20:$E$27)))))
G10: Разово | H10: =IF(B10="","",IF(G10="В месяц",MAX(1,SUMIF(Ввод!$G$20:$G$27,"TERM_MONTHS",Ввод!$E$20:$E$27)),1)) | I10: =IF(B10="","",C10*E10*H10) | J10: =IF(B10="","",IF(F10<>"",C10*F10*H10,IF(IFERROR(VLOOKUP(Ввод!$B$5,'Справочник типов'!$A$2:$J$27,10,FALSE),"По наценке")="По марже",IF(SUMIF(Ввод!$G$20:$G$27,"TARGET_MARGIN",Ввод!$E$20:$E$27)<1,I10/(1-SUMIF(Ввод!$G$20:$G$27,"TARGET_MARGIN",Ввод!$E$20:$E$27)),0),I10*(1+SUMIF(Ввод!$G$20:$G$27,"MARKUP",Ввод!$E$20:$E$27)))))
G11: Разово | H11: =IF(B11="","",IF(G11="В месяц",MAX(1,SUMIF(Ввод!$G$20:$G$27,"TERM_MONTHS",Ввод!$E$20:$E$27)),1)) | I11: =IF(B11="","",C11*E11*H11) | J11: =IF(B11="","",IF(F11<>"",C11*F11*H11,IF(IFERROR(VLOOKUP(Ввод!$B$5,'Справочник типов'!$A$2:$J$27,10,FALSE),"По наценке")="По марже",IF(SUMIF(Ввод!$G$20:$G$27,"TARGET_MARGIN",Ввод!$E$20:$E$27)<1,I11/(1-SUMIF(Ввод!$G$20:$G$27,"TARGET_MARGIN",Ввод!$E$20:$E$27)),0),I11*(1+SUMIF(Ввод!$G$20:$G$27,"MARKUP",Ввод!$E$20:$E$27)))))
G12: Разово | H12: =IF(B12="","",IF(G12="В месяц",MAX(1,SUMIF(Ввод!$G$20:$G$27,"TERM_MONTHS",Ввод!$E$20:$E$27)),1)) | I12: =IF(B12="","",C12*E12*H12) | J12: =IF(B12="","",IF(F12<>"",C12*F12*H12,IF(IFERROR(VLOOKUP(Ввод!$B$5,'Справочник типов'!$A$2:$J$27,10,FALSE),"По наценке")="По марже",IF(SUMIF(Ввод!$G$20:$G$27,"TARGET_MARGIN",Ввод!$E$20:$E$27)<1,I12/(1-SUMIF(Ввод!$G$20:$G$27,"TARGET_MARGIN",Ввод!$E$20:$E$27)),0),I12*(1+SUMIF(Ввод!$G$20:$G$27,"MARKUP",Ввод!$E$20:$E$27)))))
G13: Разово | H13: =IF(B13="","",IF(G13="В месяц",MAX(1,SUMIF(Ввод!$G$20:$G$27,"TERM_MONTHS",Ввод!$E$20:$E$27)),1)) | I13: =IF(B13="","",C13*E13*H13) | J13: =IF(B13="","",IF(F13<>"",C13*F13*H13,IF(IFERROR(VLOOKUP(Ввод!$B$5,'Справочник типов'!$A$2:$J$27,10,FALSE),"По наценке")="По марже",IF(SUMIF(Ввод!$G$20:$G$27,"TARGET_MARGIN",Ввод!$E$20:$E$27)<1,I13/(1-SUMIF(Ввод!$G$20:$G$27,"TARGET_MARGIN",Ввод!$E$20:$E$27)),0),I13*(1+SUMIF(Ввод!$G$20:$G$27,"MARKUP",Ввод!$E$20:$E$27)))))
G14: Разово | H14: =IF(B14="","",IF(G14="В месяц",MAX(1,SUMIF(Ввод!$G$20:$G$27,"TERM_MONTHS",Ввод!$E$20:$E$27)),1)) | I14: =IF(B14="","",C14*E14*H14) | J14: =IF(B14="","",IF(F14<>"",C14*F14*H14,IF(IFERROR(VLOOKUP(Ввод!$B$5,'Справочник типов'!$A$2:$J$27,10,FALSE),"По наценке")="По марже",IF(SUMIF(Ввод!$G$20:$G$27,"TARGET_MARGIN",Ввод!$E$20:$E$27)<1,I14/(1-SUMIF(Ввод!$G$20:$G$27,"TARGET_MARGIN",Ввод!$E$20:$E$27)),0),I14*(1+SUMIF(Ввод!$G$20:$G$27,"MARKUP",Ввод!$E$20:$E$27)))))
G15: Разово | H15: =IF(B15="","",IF(G15="В месяц",MAX(1,SUMIF(Ввод!$G$20:$G$27,"TERM_MONTHS",Ввод!$E$20:$E$27)),1)) | I15: =IF(B15="","",C15*E15*H15) | J15: =IF(B15="","",IF(F15<>"",C15*F15*H15,IF(IFERROR(VLOOKUP(Ввод!$B$5,'Справочник типов'!$A$2:$J$27,10,FALSE),"По наценке")="По марже",IF(SUMIF(Ввод!$G$20:$G$27,"TARGET_MARGIN",Ввод!$E$20:$E$27)<1,I15/(1-SUMIF(Ввод!$G$20:$G$27,"TARGET_MARGIN",Ввод!$E$20:$E$27)),0),I15*(1+SUMIF(Ввод!$G$20:$G$27,"MARKUP",Ввод!$E$20:$E$27)))))
G16: Разово | H16: =IF(B16="","",IF(G16="В месяц",MAX(1,SUMIF(Ввод!$G$20:$G$27,"TERM_MONTHS",Ввод!$E$20:$E$27)),1)) | I16: =IF(B16="","",C16*E16*H16) | J16: =IF(B16="","",IF(F16<>"",C16*F16*H16,IF(IFERROR(VLOOKUP(Ввод!$B$5,'Справочник типов'!$A$2:$J$27,10,FALSE),"По наценке")="По марже",IF(SUMIF(Ввод!$G$20:$G$27,"TARGET_MARGIN",Ввод!$E$20:$E$27)<1,I16/(1-SUMIF(Ввод!$G$20:$G$27,"TARGET_MARGIN",Ввод!$E$20:$E$27)),0),I16*(1+SUMIF(Ввод!$G$20:$G$27,"MARKUP",Ввод!$E$20:$E$27)))))
G17: Разово | H17: =IF(B17="","",IF(G17="В месяц",MAX(1,SUMIF(Ввод!$G$20:$G$27,"TERM_MONTHS",Ввод!$E$20:$E$27)),1)) | I17: =IF(B17="","",C17*E17*H17) | J17: =IF(B17="","",IF(F17<>"",C17*F17*H17,IF(IFERROR(VLOOKUP(Ввод!$B$5,'Справочник типов'!$A$2:$J$27,10,FALSE),"По наценке")="По марже",IF(SUMIF(Ввод!$G$20:$G$27,"TARGET_MARGIN",Ввод!$E$20:$E$27)<1,I17/(1-SUMIF(Ввод!$G$20:$G$27,"TARGET_MARGIN",Ввод!$E$20:$E$27)),0),I17*(1+SUMIF(Ввод!$G$20:$G$27,"MARKUP",Ввод!$E$20:$E$27)))))
... G25: Разово | H25: =IF(B25="","",IF(G25="В месяц",MAX(1,SUMIF(Ввод!$G$20:$G$27,"TERM_MONTHS",Ввод!$E$20:$E$27)),1)) | I25: =IF(B25="","",C25*E25*H25) | J25: =IF(B25="","",IF(F25<>"",C25*F25*H25,IF(IFERROR(VLOOKUP(Ввод!$B$5,'Справочник типов'!$A$2:$J$27,10,FALSE),"По наценке")="По марже",IF(SUMIF(Ввод!$G$20:$G$27,"TARGET_MARGIN",Ввод!$E$20:$E$27)<1,I25/(1-SUMIF(Ввод!$G$20:$G$27,"TARGET_MARGIN",Ввод!$E$20:$E$27)),0),I25*(1+SUMIF(Ввод!$G$20:$G$27,"MARKUP",Ввод!$E$20:$E$27)))))

Sheet Справочник типов
A1: Код типа | B1: Направление | C1: Продукт | D1: Описание | E1: Категория | F1: Ориентир срока, мес. | G1: Тип сделки | H1: Расчётная модель | I1: База часов по умолчанию | J1: Метод внешних затрат
A2: SUP_Complex | B2: DIT | C2: Комплексная поддержка | D2: Комплексное обслуживание ИТ-инфраструктуры | E2: Услуги | F2: 12 | G2: Возобновляемая | H2: Поддержка | I2: В месяц | J2: По наценке
A3: SUP_L1 | B3: DIT | C3: Колл-центр, поддержка | D3: Первая линия и обработка обращений | E3: Услуги | F3: 6 | G3: Разовая | H3: Поддержка | I3: В месяц | J3: По наценке
A4: SUP_L2 | B4: DIT | C4: Поддержка пользователей и рабочих мест | D4: Вторая линия и поддержка рабочих мест | E4: Услуги | F4: 12 | G4: Возобновляемая | H4: Поддержка | I4: В месяц | J4: По наценке
A5: SUP_L3_HW | B5: DIT | C5: Инфраструктура с аппаратной поддержкой | D5: Третья линия и аппаратная поддержка | E5: Услуги | F5: 12 | G5: Возобновляемая | H5: Поддержка | I5: В месяц | J5: По наценке
A6: SUP_L3_SW | B6: DIT | C6: Инфраструктура без аппаратной поддержки | D6: Третья линия без аппаратной поддержки | E6: Услуги | F6: 12 | G6: Возобновляемая | H6: Поддержка | I6: В месяц | J6: По наценке
A7: SUP_SUPPLIER | B7: DIT | C7: Проекты с подрядом | D7: Услуги с существенной долей внешнего подрядчика | E7: Услуги | F7: 12 | G7: Возобновляемая | H7: Подряд | I7: В месяц | J7: По марже
A8: SUP_IT_Audit | B8: DIT | C8: ИТ-аудит | D8: Обследование инфраструктуры и бизнес-процессов | E8: Услуги | F8: 3 | G8: Разовая | H8: Аудит | I8: Всего | J8: По наценке
A9: SUP_IT_Consulting | B9: DIT | C9: ИТ-консалтинг | D9: Архитектура, DR, сети, СРК, мониторинг, регламенты | E9: Услуги | F9: 3 | G9: Разовая | H9: Консалтинг | I9: Всего | J9: По наценке
A10: SUP_IT_Implementation | B10: DIT | C10: Внедрение инфраструктуры | D10: Виртуализация, инфраструктурные сервисы, миграции и обновления | E10: Услуги | F10: 3 | G10: Разовая | H10: Внедрение | I10: Всего | J10: По наценке
A11: SUP_Cloud_Consulting | B11: DIT | C11: Облачный консалтинг | D11: Архитектура, миграции и проектирование облачного решения | E11: Услуги | F11: 3 | G11: Разовая | H11: Консалтинг | I11: Всего | J11: По наценке
A12: SUP_Cloud_IaaS | B12: DIT | C12: Облачные ресурсы IaaS | D12: Продажа облачных ресурсов и сервисов | E12: Cloud | F12: 12 | G12: Возобновляемая | H12: Облако | I12: В месяц | J12: По марже
A13: SUP_Cloud_PaaS | B13: DIT | C13: Облачная платформа PaaS | D13: IaaS, базовые сервисы, лицензии и поддержка | E13: Cloud | F13: 12 | G13: Возобновляемая | H13: Облако | I13: В месяц | J13: По марже
... A27: SEC_Complex | B27: SEC | C27: Комплексная поддержка | D27: Комплексная поддержка решений ИБ | E27: Услуги | F27: 4 | G27: Разовая | H27: Поддержка | I27: В месяц | J27: По наценке

Sheet Параметры типов
A1: Код типа | B1: Слот | C1: Параметр | D1: Ед. | E1: Значение по умолчанию | F1: Обязателен | G1: Код влияния | H1: Как влияет
A2: SUP_Complex | B2: 1 | C2: Пользователей / рабочих мест | D2: шт. | E2: 1 | F2: Да | G2: QTY | H2: Используется для строк «На единицу»
A3: SUP_Complex | B3: 2 | C3: Срок обслуживания | D3: мес. | E3: 12 | F3: Да | G3: TERM_MONTHS | H3: Множитель для ежемесячных работ
A4: SUP_Complex | B4: 3 | C4: Окно поддержки | D4: ч/нед. | E4: 40 | F4: Нет | G4: INFO | H4: Контекст нагрузки и сменности
A5: SUP_Complex | B5: 4 | C5: Обращений / событий в месяц | D5: шт. | F5: Нет | G5: INFO | H5: Контекст нагрузки
A6: SUP_Complex | B6: 5 | C6: SLA реакции | D6: ч | F6: Нет | G6: INFO | H6: Контекст уровня сервиса
A7: SUP_Complex | B7: 6 | C7: Параллельная команда | D7: FTE | E7: 1 | F7: Да | G7: PARALLEL_FTE | H7: Оценка календарной нагрузки
A8: SUP_Complex | B8: 7 | C8: Резерв рисков | D8: % | E8: 0 | F8: Нет | G8: RISK_PCT | H8: Добавляется к трудозатратам
A9: SUP_Complex | B9: 8 | C9: Наценка внешних затрат | D9: % | E9: 0 | F9: Нет | G9: MARKUP | H9: Применяется при отсутствии ручной цены
A10: SUP_L1 | B10: 1 | C10: Пользователей / абонентов | D10: шт. | E10: 1 | F10: Да | G10: QTY | H10: Используется для строк «На единицу»
A11: SUP_L1 | B11: 2 | C11: Срок обслуживания | D11: мес. | E11: 6 | F11: Да | G11: TERM_MONTHS | H11: Множитель для ежемесячных работ
A12: SUP_L1 | B12: 3 | C12: Окно поддержки | D12: ч/нед. | E12: 40 | F12: Нет | G12: INFO | H12: Контекст нагрузки и сменности
A13: SUP_L1 | B13: 4 | C13: Обращений / событий в месяц | D13: шт. | F13: Нет | G13: INFO | H13: Контекст нагрузки
A14: SUP_L1 | B14: 5 | C14: SLA реакции | D14: ч | F14: Нет | G14: INFO | H14: Контекст уровня сервиса
A15: SUP_L1 | B15: 6 | C15: Параллельная команда | D15: FTE | E15: 1 | F15: Да | G15: PARALLEL_FTE | H15: Оценка календарной нагрузки
A16: SUP_L1 | B16: 7 | C16: Резерв рисков | D16: % | E16: 0 | F16: Нет | G16: RISK_PCT | H16: Добавляется к трудозатратам
A17: SUP_L1 | B17: 8 | C17: Наценка внешних затрат | D17: % | E17: 0 | F17: Нет | G17: MARKUP | H17: Применяется при отсутствии ручной цены
A18: SUP_L2 | B18: 1 | C18: Рабочих мест | D18: шт. | E18: 1 | F18: Да | G18: QTY | H18: Используется для строк «На единицу»
A19: SUP_L2 | B19: 2 | C19: Срок обслуживания | D19: мес. | E19: 12 | F19: Да | G19: TERM_MONTHS | H19: Множитель для ежемесячных работ
A20: SUP_L2 | B20: 3 | C20: Окно поддержки | D20: ч/нед. | E20: 40 | F20: Нет | G20: INFO | H20: Контекст нагрузки и сменности
A21: SUP_L2 | B21: 4 | C21: Обращений / событий в месяц | D21: шт. | F21: Нет | G21: INFO | H21: Контекст нагрузки
A22: SUP_L2 | B22: 5 | C22: SLA реакции | D22: ч | F22: Нет | G22: INFO | H22: Контекст уровня сервиса
A23: SUP_L2 | B23: 6 | C23: Параллельная команда | D23: FTE | E23: 1 | F23: Да | G23: PARALLEL_FTE | H23: Оценка календарной нагрузки
A24: SUP_L2 | B24: 7 | C24: Резерв рисков | D24: % | E24: 0 | F24: Нет | G24: RISK_PCT | H24: Добавляется к трудозатратам
A25: SUP_L2 | B25: 8 | C25: Наценка внешних затрат | D25: % | E25: 0 | F25: Нет | G25: MARKUP | H25: Применяется при отсутствии ручной цены
A26: SUP_L3_HW | B26: 1 | C26: Единиц оборудования | D26: шт. | E26: 1 | F26: Да | G26: QTY | H26: Используется для строк «На единицу»
A27: SUP_L3_HW | B27: 2 | C27: Срок обслуживания | D27: мес. | E27: 12 | F27: Да | G27: TERM_MONTHS | H27: Множитель для ежемесячных работ
A28: SUP_L3_HW | B28: 3 | C28: Окно поддержки | D28: ч/нед. | E28: 40 | F28: Нет | G28: INFO | H28: Контекст нагрузки и сменности
A29: SUP_L3_HW | B29: 4 | C29: Обращений / событий в месяц | D29: шт. | F29: Нет | G29: INFO | H29: Контекст нагрузки
A30: SUP_L3_HW | B30: 5 | C30: SLA реакции | D30: ч | F30: Нет | G30: INFO | H30: Контекст уровня сервиса
A31: SUP_L3_HW | B31: 6 | C31: Параллельная команда | D31: FTE | E31: 1 | F31: Да | G31: PARALLEL_FTE | H31: Оценка календарной нагрузки
A32: SUP_L3_HW | B32: 7 | C32: Резерв рисков | D32: % | E32: 0 | F32: Нет | G32: RISK_PCT | H32: Добавляется к трудозатратам
A33: SUP_L3_HW | B33: 8 | C33: Наценка внешних затрат | D33: % | E33: 0 | F33: Нет | G33: MARKUP | H33: Применяется при отсутствии ручной цены
A34: SUP_L3_SW | B34: 1 | C34: Серверов / систем | D34: шт. | E34: 1 | F34: Да | G34: QTY | H34: Используется для строк «На единицу»
A35: SUP_L3_SW | B35: 2 | C35: Срок обслуживания | D35: мес. | E35: 12 | F35: Да | G35: TERM_MONTHS | H35: Множитель для ежемесячных работ
A36: SUP_L3_SW | B36: 3 | C36: Окно поддержки | D36: ч/нед. | E36: 40 | F36: Нет | G36: INFO | H36: Контекст нагрузки и сменности
A37: SUP_L3_SW | B37: 4 | C37: Обращений / событий в месяц | D37: шт. | F37: Нет | G37: INFO | H37: Контекст нагрузки
A38: SUP_L3_SW | B38: 5 | C38: SLA реакции | D38: ч | F38: Нет | G38: INFO | H38: Контекст уровня сервиса
A39: SUP_L3_SW | B39: 6 | C39: Параллельная команда | D39: FTE | E39: 1 | F39: Да | G39: PARALLEL_FTE | H39: Оценка календарной нагрузки
A40: SUP_L3_SW | B40: 7 | C40: Резерв рисков | D40: % | E40: 0 | F40: Нет | G40: RISK_PCT | H40: Добавляется к трудозатратам
A41: SUP_L3_SW | B41: 8 | C41: Наценка внешних затрат | D41: % | E41: 0 | F41: Нет | G41: MARKUP | H41: Применяется при отсутствии ручной цены
A42: SUP_SUPPLIER | B42: 1 | C42: Объём подрядных работ | D42: ед. | E42: 1 | F42: Да | G42: QTY | H42: Используется для строк «На единицу»
A43: SUP_SUPPLIER | B43: 2 | C43: Срок договора | D43: мес. | E43: 12 | F43: Да | G43: TERM_MONTHS | H43: Множитель ежемесячных затрат
A44: SUP_SUPPLIER | B44: 3 | C44: Целевая маржа внешних затрат | D44: % | F44: Да | G44: TARGET_MARGIN | H44: Обязательна, если цена не задана вручную
A45: SUP_SUPPLIER | B45: 4 | C45: Срок мобилизации подрядчика | D45: раб. дн. | E45: 0 | F45: Нет | G45: LEAD_DAYS | H45: Добавляется к сроку
A46: SUP_SUPPLIER | B46: 5 | C46: Сложность координации | D46: коэф. | E46: 1 | F46: Да | G46: COMPLEXITY | H46: Множитель внутренних часов
A47: SUP_SUPPLIER | B47: 6 | C47: Параллельная команда | D47: FTE | E47: 1 | F47: Да | G47: PARALLEL_FTE | H47: Оценка срока
A48: SUP_SUPPLIER | B48: 7 | C48: Резерв рисков | D48: % | E48: 0 | F48: Нет | G48: RISK_PCT | H48: Добавляется к внутренним часам
A49: SUP_SUPPLIER | B49: 8 | C49: SLA подрядчика | D49: текст | F49: Нет | G49: INFO | H49: Контекст проверки
A50: SUP_IT_Audit | B50: 1 | C50: Систем / контуров обследования | D50: шт. | E50: 1 | F50: Да | G50: QTY | H50: Используется только для строк с базой «На единицу»
A51: SUP_IT_Audit | B51: 2 | C51: Площадок | D51: шт. | E51: 1 | F51: Нет | G51: INFO | H51: Контекст для декомпозиции и проверки часов
A52: SUP_IT_Audit | B52: 3 | C52: Глубина обследования | D52: коэф. | E52: 1 | F52: Да | G52: COMPLEXITY | H52: Множитель трудозатрат
A53: SUP_IT_Audit | B53: 4 | C53: Параллельных специалистов | D53: FTE | E53: 1 | F53: Да | G53: PARALLEL_FTE | H53: Используется при оценке календарного срока
A54: SUP_IT_Audit | B54: 5 | C54: Резерв рисков | D54: % | E54: 0 | F54: Нет | G54: RISK_PCT | H54: Добавляется к трудозатратам
A55: SUP_IT_Audit | B55: 6 | C55: Срок согласований | D55: раб. дн. | E55: 0 | F55: Нет | G55: LEAD_DAYS | H55: Добавляется к сроку разового проекта
A56: SUP_IT_Audit | B56: 7 | C56: Размер выборки | D56: объектов | F56: Нет | G56: INFO | H56: Контекст для экспертной проверки
A57: SUP_IT_Audit | B57: 8 | C57: Объём документации | D57: док. | F57: Нет | G57: INFO | H57: Контекст для экспертной проверки
A58: SUP_IT_Consulting | B58: 1 | C58: Архитектурных доменов | D58: шт. | E58: 1 | F58: Да | G58: QTY | H58: Используется для строк «На единицу»
A59: SUP_IT_Consulting | B59: 2 | C59: Площадок / организаций | D59: шт. | E59: 1 | F59: Нет | G59: INFO | H59: Контекст оценки
A60: SUP_IT_Consulting | B60: 3 | C60: Рабочих сессий | D60: шт. | F60: Нет | G60: INFO | H60: Контекст оценки
A61: SUP_IT_Consulting | B61: 4 | C61: Сложность | D61: коэф. | E61: 1 | F61: Да | G61: COMPLEXITY | H61: Множитель трудозатрат
A62: SUP_IT_Consulting | B62: 5 | C62: Параллельных специалистов | D62: FTE | E62: 1 | F62: Да | G62: PARALLEL_FTE | H62: Оценка срока
A63: SUP_IT_Consulting | B63: 6 | C63: Резерв рисков | D63: % | E63: 0 | F63: Нет | G63: RISK_PCT | H63: Добавляется к трудозатратам
A64: SUP_IT_Consulting | B64: 7 | C64: Срок согласований | D64: раб. дн. | E64: 0 | F64: Нет | G64: LEAD_DAYS | H64: Добавляется к сроку
A65: SUP_IT_Consulting | B65: 8 | C65: Наценка внешних затрат | D65: % | E65: 0 | F65: Нет | G65: MARKUP | H65: Применяется при отсутствии ручной цены
A66: SUP_IT_Implementation | B66: 1 | C66: Объектов / сервисов | D66: шт. | E66: 1 | F66: Да | G66: QTY | H66: Используется для строк «На единицу»
A67: SUP_IT_Implementation | B67: 2 | C67: Площадок | D67: шт. | E67: 1 | F67: Нет | G67: INFO | H67: Контекст оценки
A68: SUP_IT_Implementation | B68: 3 | C68: Интеграций / миграционных потоков | D68: шт. | F68: Нет | G68: INFO | H68: Контекст оценки
A69: SUP_IT_Implementation | B69: 4 | C69: Сложность | D69: коэф. | E69: 1 | F69: Да | G69: COMPLEXITY | H69: Множитель трудозатрат
A70: SUP_IT_Implementation | B70: 5 | C70: Параллельных специалистов | D70: FTE | E70: 1 | F70: Да | G70: PARALLEL_FTE | H70: Оценка срока
A71: SUP_IT_Implementation | B71: 6 | C71: Резерв рисков | D71: % | E71: 0 | F71: Нет | G71: RISK_PCT | H71: Добавляется к трудозатратам
A72: SUP_IT_Implementation | B72: 7 | C72: Срок поставок / доступов | D72: раб. дн. | E72: 0 | F72: Нет | G72: LEAD_DAYS | H72: Добавляется к сроку
A73: SUP_IT_Implementation | B73: 8 | C73: Наценка внешних затрат | D73: % | E73: 0 | F73: Нет | G73: MARKUP | H73: Применяется при отсутствии ручной цены
A74: SUP_Cloud_Consulting | B74: 1 | C74: Облачных доменов / потоков | D74: шт. | E74: 1 | F74: Да | G74: QTY | H74: Используется для строк «На единицу»
A75: SUP_Cloud_Consulting | B75: 2 | C75: Площадок / организаций | D75: шт. | E75: 1 | F75: Нет | G75: INFO | H75: Контекст оценки
A76: SUP_Cloud_Consulting | B76: 3 | C76: Рабочих сессий | D76: шт. | F76: Нет | G76: INFO | H76: Контекст оценки
A77: SUP_Cloud_Consulting | B77: 4 | C77: Сложность | D77: коэф. | E77: 1 | F77: Да | G77: COMPLEXITY | H77: Множитель трудозатрат
A78: SUP_Cloud_Consulting | B78: 5 | C78: Параллельных специалистов | D78: FTE | E78: 1 | F78: Да | G78: PARALLEL_FTE | H78: Оценка срока
A79: SUP_Cloud_Consulting | B79: 6 | C79: Резерв рисков | D79: % | E79: 0 | F79: Нет | G79: RISK_PCT | H79: Добавляется к трудозатратам
A80: SUP_Cloud_Consulting | B80: 7 | C80: Срок согласований | D80: раб. дн. | E80: 0 | F80: Нет | G80: LEAD_DAYS | H80: Добавляется к сроку
A81: SUP_Cloud_Consulting | B81: 8 | C81: Наценка внешних затрат | D81: % | E81: 0 | F81: Нет | G81: MARKUP | H81: Применяется при отсутствии ручной цены
A82: SUP_Cloud_IaaS | B82: 1 | C82: Ресурсных единиц / ВМ | D82: ед. | E82: 1 | F82: Да | G82: QTY | H82: Используется для строк «На единицу»
A83: SUP_Cloud_IaaS | B83: 2 | C83: Срок подписки | D83: мес. | E83: 12 | F83: Да | G83: TERM_MONTHS | H83: Множитель ежемесячных работ и затрат
A84: SUP_Cloud_IaaS | B84: 3 | C84: Целевая маржа внешних затрат | D84: % | F84: Да | G84: TARGET_MARGIN | H84: Обязательна, если цена не задана вручную
A85: SUP_Cloud_IaaS | B85: 4 | C85: Доступность / SLA | D85: % | F85: Нет | G85: INFO | H85: Контекст конфигурации
A86: SUP_Cloud_IaaS | B86: 5 | C86: Трафик / объём данных | D86: ТБ/мес. | F86: Нет | G86: INFO | H86: Контекст затрат провайдера
A87: SUP_Cloud_IaaS | B87: 6 | C87: Срок запуска | D87: раб. дн. | E87: 0 | F87: Нет | G87: LEAD_DAYS | H87: Добавляется к сроку запуска
A88: SUP_Cloud_IaaS | B88: 7 | C88: Параллельная команда | D88: FTE | E88: 1 | F88: Да | G88: PARALLEL_FTE | H88: Оценка запуска
A89: SUP_Cloud_IaaS | B89: 8 | C89: Резерв рисков | D89: % | E89: 0 | F89: Нет | G89: RISK_PCT | H89: Добавляется к трудозатратам
A90: SUP_Cloud_PaaS | B90: 1 | C90: Экземпляров платформы | D90: ед. | E90: 1 | F90: Да | G90: QTY | H90: Используется для строк «На единицу»
A91: SUP_Cloud_PaaS | B91: 2 | C91: Срок подписки | D91: мес. | E91: 12 | F91: Да | G91: TERM_MONTHS | H91: Множитель ежемесячных работ и затрат
A92: SUP_Cloud_PaaS | B92: 3 | C92: Целевая маржа внешних затрат | D92: % | F92: Да | G92: TARGET_MARGIN | H92: Обязательна, если цена не задана вручную
A93: SUP_Cloud_PaaS | B93: 4 | C93: Доступность / SLA | D93: % | F93: Нет | G93: INFO | H93: Контекст конфигурации
A94: SUP_Cloud_PaaS | B94: 5 | C94: Трафик / объём данных | D94: ТБ/мес. | F94: Нет | G94: INFO | H94: Контекст затрат провайдера
A95: SUP_Cloud_PaaS | B95: 6 | C95: Срок запуска | D95: раб. дн. | E95: 0 | F95: Нет | G95: LEAD_DAYS | H95: Добавляется к сроку запуска
A96: SUP_Cloud_PaaS | B96: 7 | C96: Параллельная команда | D96: FTE | E96: 1 | F96: Да | G96: PARALLEL_FTE | H96: Оценка запуска
A97: SUP_Cloud_PaaS | B97: 8 | C97: Резерв рисков | D97: % | E97: 0 | F97: Нет | G97: RISK_PCT | H97: Добавляется к трудозатратам
A98: SUP_Cloud_SaaS | B98: 1 | C98: Пользователей / подписок | D98: ед. | E98: 1 | F98: Да | G98: QTY | H98: Используется для строк «На единицу»
A99: SUP_Cloud_SaaS | B99: 2 | C99: Срок подписки | D99: мес. | E99: 12 | F99: Да | G99: TERM_MONTHS | H99: Множитель ежемесячных работ и затрат
A100: SUP_Cloud_SaaS | B100: 3 | C100: Целевая маржа внешних затрат | D100: % | F100: Да | G100: TARGET_MARGIN | H100: Обязательна, если цена не задана вручную
...

Sheet Справочник ролей
A1: Код роли | B1: Направление | C1: Роль | D1: Ставка продажи, руб./ч | E1: Себестоимость, руб./ч | F1: Источник | H1: Направление | I1: Средняя ставка продажи | J1: Средняя себестоимость
A2: 6034 | B2: SEC | C2: Тимлид-Архитектор ИБ | #6034 | D2: 7500 | E2: 6506 | F2: Ставки.jpg | H2: SEC | I2: 5975 | J2: 5384
A3: 6035 | B3: SEC | C3: Ведущий инженер ИБ | #6035 | D3: 5500 | E3: 4566 | F3: Ставки.jpg | H3: DIT / SUPP | I3: 3466 | J3: 2914
A4: 6036 | B4: SEC | C4: Пентестер | #6036 | D4: 5500 | E4: 5200 | F4: Ставки.jpg | H4: Примечание | I4: Средние значения сохранены справочно | J4: В строках расчёта используются ставки конкретных ролей
A5: 6037 | B5: SEC | C5: Ведущий Архитектор ИБ | #6037 | D5: 6500 | E5: 5559 | F5: Ставки.jpg
A6: 6039 | B6: SEC | C6: Архитектор ИБ | #6039 | D6: 5850 | E6: 4905 | F6: Ставки.jpg
A7: 472 | B7: DIT | C7: Руководитель дежурной смены | #472 | D7: 4500 | E7: 4169 | F7: Ставки.jpg
A8: 473 | B8: DIT | C8: Супервизор - Руководитель группы | #473 | D8: 2500 | E8: 1745 | F8: Ставки.jpg
A9: 474 | B9: DIT | C9: L1 Инженер дежурной смены | #474 | D9: 2100 | E9: 1424 | F9: Ставки.jpg
A10: 475 | B10: DIT | C10: L2 Инженер технической поддержки | #475 | D10: 3000 | E10: 2203 | F10: Ставки.jpg
A11: 476 | B11: DIT | C11: Руководитель 3 линии | #476 | D11: 5800 | E11: 5609 | F11: Ставки.jpg
A12: 477 | B12: DIT | C12: Тимлид - Руководитель группы | #477 | D12: 5800 | E12: 5196 | F12: Ставки.jpg
A13: 478 | B13: DIT | C13: L3 Сетевой инженер | #478 | D13: 4200 | E13: 3380 | F13: Ставки.jpg
A14: 479 | B14: DIT | C14: L3 Windows инженер | #479 | D14: 4200 | E14: 3736 | F14: Ставки.jpg
A15: 480 | B15: DIT | C15: L3 Архитектор | #480 | D15: 6500 | E15: 5695 | F15: Ставки.jpg
A16: 1202 | B16: DIT | C16: L3 DevOps-инженер | #1202 | D16: 4200 | E16: 2755 | F16: Ставки.jpg
... A20: 1207 | B20: DIT | C20: L3 DBA инженер | #1207 | D20: 4200 | E20: 2755 | F20: Пример расчёта заказчика

Sheet Проверки
A1: Контроли модели
A3: MODEL STATUS | B3: =IF(COUNTIF(E6:E14,"FAIL")>0,"FAIL","PASS") -> FAIL
A5: Проверка | B5: Дельта / значение | C5: Где исправить | D5: Примечание | E5: Статус
A6: Тип проекта распознан | B6: =COUNTIF('Справочник типов'!$A$2:$A$27,Ввод!$B$5) -> 0 | C6: Ввод!B5 | D6: Должно быть 1 | E6: =IF(B6=1,"PASS","FAIL") -> FAIL
A7: Строки с отсутствующей ставкой | B7: =COUNTIF(Расчёт!$T$6:$T$105,"*СТАВКУ*") -> 0 | C7: Расчёт!E:I | D7: 0 либо ручные ставки | E7: =IF(B7=0,"PASS","FAIL") -> PASS
A8: Строки с некорректными часами | B8: =COUNTIF(Расчёт!$T$6:$T$105,"*ЧАСЫ*") -> 0 | C8: Расчёт!F:F | D8: Должно быть 0 | E8: =IF(B8=0,"PASS","FAIL") -> PASS
A9: Незаполненные обязательные параметры | B9: =COUNTIFS(Ввод!$F$20:$F$27,"Да",Ввод!$E$20:$E$27,"") -> 0 | C9: Ввод!D20:D27 | D9: Должно быть 0 | E9: =IF(B9=0,"PASS","FAIL") -> PASS
A10: Срок для ежемесячных строк | B10: =IF(COUNTIF(Расчёт!$N$6:$N$105,"*месяц*")+COUNTIFS('Внешние затраты'!$G$6:$G$25,"В месяц",'Внешние затраты'!$I$6:$I$25,">0")=0,1,SUMIF(Ввод!$G$20:$G$27,"TERM_MONTHS",Ввод!$E$20:$E$27)) -> 1 | C10: Ввод: срок договора | D10: Должен быть > 0 при ежемесячных строках с ненулевой стоимостью | E10: =IF(B10>0,"PASS","FAIL") -> PASS
A11: Маржа внешних затрат | B11: =IF(AND(IFERROR(VLOOKUP(Ввод!$B$5,'Справочник типов'!$A$2:$J$27,10,FALSE),"")="По марже",SUM('Внешние затраты'!$I$6:$I$25)>0),SUMIF(Ввод!$G$20:$G$27,"TARGET_MARGIN",Ввод!$E$20:$E$27),0.01) -> 0.01 | C11: Ввод: целевая маржа | D11: 0 < маржа < 95% при наличии внешних затрат | E11: =IF(AND(B11>0,B11<0.95),"PASS","FAIL") -> PASS
A12: Рабочих часов в дне | B12: =Ввод!$B$11 -> 8 | C12: Ввод!B11 | D12: Должно быть > 0 | E12: =IF(B12>0,"PASS","FAIL") -> PASS
A13: Уверенность оценки | B13: =Ввод!$B$8 -> 0.7 | C13: Ввод!B8 | D13: Менее 70% — бюджетная оценка | E13: =IF(B13>=0.7,"PASS","WARN") -> PASS
A14: Строки с отрицательными исходными часами | B14: =COUNTIF(Расчёт!$F$6:$F$105,"<0") -> 0 | C14: Расчёт!F:F | D14: Должно быть 0 | E14: =IF(B14=0,"PASS","FAIL") -> PASS

Sheet Источники
A1: Источники и использование данных
A3: Источник | B3: Формат | C3: Что использовано | D3: Ограничения / примечание | E3: Дата анализа
